Workbook

Sheet Products
A1: Source SI No. | B1: Product Category | C1: Partner Company | D1: Country | E1: Product / Model | F1: Planned DIWAN Category Page Path | G1: Website Page Scope | H1: Architecture Updated On | I1: Product Listing Title | J1: Product Listing / Anchor Slug | K1: Short Product Listing Description | L1: Product Listing / Category SEO Support Copy | M1: Product Listing Call to Action | N1: Product Listing Content Status | O1: Product Listing Overview | P1: Key Features & Benefits | Q1: Technical Specifications | R1: Applications & Industries | S1: Primary Image URL | T1: Image Alt Text | U1: Datasheet / Brochure URL | V1: Additional Documents | W1: Related Products | X1: Enquiry Route | Y1: Target SEO Keywords | Z1: Verified Content Source URL | AA1: Source Verified On | AB1: Approval Owner | AC1: Product Listing Content Readiness | AD1: Review Notes | AE1: Additional Image URLs | AF1: Product Video URL | AG1: Commercial Availability Policy | AH1: Lead Time / Delivery Wording | AI1: Public Document Access Rule
A2: 1 | B2: Thermal Analysis | C2: ThermCon Scientific | D2: Germany | E2: STA 1000 / 1600 Simultaneous Thermal Analyzer (TGA + DSC) | F2: /products/thermal-analysis | G2: One page per product category | H2: 46257 | I2: STA 1000 / 1600 Simultaneous Thermal Analyzer (TGA + DSC) | DIWAN Engineering & Technology Company | J2: sta-1000-1600-simultaneous-thermal-analyzer-tga-dsc | K2: The STA 1000 / 1600 combines thermogravimetric and differential scanning calorimetry in one platform for simultaneous mass-change and heat-flow analysis under controlled temperature and atmosphere conditions. | L2: STA 1000 / 1600 Simultaneous Thermal Analyzer (TGA + DSC) from ThermCon Scientific: key capabilities, technical specifications and applications. Request configuration advice and a quotation from DIWAN. | M2: Request technical information or a quote | N2: Draft complete - technical approval and assets pending | O2: ThermCon Scientific's STA 1000 / 1600 is a simultaneous thermal analyzer that records TG and DSC signals in a single test. Its automatic lifting furnace, digital mass-flow control and analysis software support material characterization, stability studies and quality control. | P2: Simultaneous TGA and DSC measurement; automatic lifting furnace; digital mass-flow control; rapid external-water cooling; 0.01 µg weighing resolution; intelligent analysis software; IR-system compatibility. | Q2: Temperature range: room temperature to 1250°C or 1550°C; heating rate: 0.1–100°C/min; cooling rate: -0.1 to -40°C/min; weighing range: 0.01 mg–3 g, expandable to 50 g; DSC range/sensitivity: ±1000 mW / 0.0001 mW; programmable isothermal testing. | R2: Polymers, composites, resins, coatings, metals, ceramics, pharmaceuticals and chemicals; thermal stability, purity, phase transitions, decomposition, composition and reaction-kinetics studies. | S2: https://www.thermconscientific.com/Resim/2ffa86104b_20252165327672.jpg | T2: STA 1000 / 1600 Simultaneous Thermal Analyzer (TGA + DSC) from ThermCon Scientific | V2: No public downloadable brochure identified during review; provide documents on request after manufacturer rights and revision checks. | W2: TGA 1000 / 1600; DSC 600; DTA 1000 / 1600; TC3500S | X2: Thermal Analysis enquiry → website group enquiry form → category owner assignment | Y2: STA 1000 / 1600 Simultaneous Thermal Analyzer (TGA + DSC), Thermal Analysis, ThermCon Scientific, laboratory instrument, DIWAN | Z2: https://www.thermconscientific.com/EN%2C15/sta-1500-simultaneous-thermal-analyzer-tga--dsc.html | AA2: 46257 | AB2: Product Team / Technical Reviewer | AC2: =IF(AND(O2<>"",P2<>"",R2<>"",T2<>"",X2<>"",Y2<>"",Z2<>"",AA2<>"",AB2<>""),IF(AND(Q2<>"",S2<>"",U2<>""),"Ready for approval","Content drafted - assets/specs pending"),IF(COUNTA(O2:AB2)=0,"Not started","In progress")) -> Content drafted - assets/specs pending | AD2: Exact manufacturer product page verified. Product page URL contains 'STA 1500' while the displayed product title is STA 1000 / 1600; confirm naming before publication. Source reviewed 2026-08-23. Primary image and downloadable brochure assets remain open. | AG2: Availability, configuration and commercial supply are subject to confirmation by DIWAN and the manufacturer. | AH2: Lead time is confirmed in the formal quotation; do not publish a fixed delivery commitment. | AI2: Publish manufacturer documents only when public access and reuse are permitted; otherwise provide controlled access on request.
A3: =IF(B3=B2,A2,A2+1) -> 1 | B3: Thermal Analysis | C3: ThermCon Scientific | D3: Germany | E3: TGA 1000 / 1600 Thermogravimetric Analyzer | F3: /products/thermal-analysis | G3: One page per product category | H3: 46257 | I3: TGA 1000 / 1600 Thermogravimetric Analyzer | DIWAN Engineering & Technology Company | J3: tga-1000-1600-thermogravimetric-analyzer | K3: The TGA 1000 / 1600 measures sample mass change during programmed heating and cooling to support thermal stability, decomposition, oxidation and composition analysis. | L3: TGA 1000 / 1600 Thermogravimetric Analyzer from ThermCon Scientific: key capabilities, technical specifications and applications. Request configuration advice and a quotation from DIWAN. | M3: Request technical information or a quote | N3: Draft complete - technical approval and assets pending | O3: ThermCon Scientific's TGA 1000 / 1600 is an automatic-lifting thermogravimetric analyzer for monitoring material mass changes as a function of temperature or time. Controlled gas flow, high-resolution weighing and integrated software support repeatable research and quality-control workflows. | P3: Automatic lifting furnace; high-resolution microbalance; programmed temperature control; automatic atmosphere control; rapid cooling; real-time software analysis; optional coupling with infrared analysis. | Q3: Temperature range: room temperature to 1250°C or 1550°C; temperature resolution: 0.001°C; heating rate: 0.1–100°C/min; cooling rate: -0.1 to -40°C/min; weighing range: 0.01 mg–3 g, expandable to 50 g; weighing resolution: 0.01 µg. | R3: Polymers, chemicals, pharmaceuticals, ceramics, metals and composites; mass-loss, moisture, ash, oxidation, decomposition, thermal stability, purity and composition testing. | S3: https://www.thermconscientific.com/Resim/8268fb1cf5_202432418569359.jpg | T3: TGA 1000 / 1600 Thermogravimetric Analyzer from ThermCon Scientific | V3: No public downloadable brochure identified during review; provide documents on request after manufacturer rights and revision checks. | W3: STA 1000 / 1600; DSC 600; DTA 1000 / 1600; TC3500S | X3: Thermal Analysis enquiry → website group enquiry form → category owner assignment | Y3: TGA 1000 / 1600 Thermogravimetric Analyzer, Thermal Analysis, ThermCon Scientific, laboratory instrument, DIWAN | Z3: https://www.thermconscientific.com/EN%2C20/tga-1000--1600-thermogravimetric-analyzer-tga.html | AA3: 46257 | AB3: Product Team / Technical Reviewer | AC3: =IF(AND(O3<>"",P3<>"",R3<>"",T3<>"",X3<>"",Y3<>"",Z3<>"",AA3<>"",AB3<>""),IF(AND(Q3<>"",S3<>"",U3<>""),"Ready for approval","Content drafted - assets/specs pending"),IF(COUNTA(O3:AB3)=0,"Not started","In progress")) -> Content drafted - assets/specs pending | AD3: Exact manufacturer product page verified; technical approval and publication assets remain required. Source reviewed 2026-08-23. Primary image and downloadable brochure assets remain open. | AG3: Availability, configuration and commercial supply are subject to confirmation by DIWAN and the manufacturer. | AH3: Lead time is confirmed in the formal quotation; do not publish a fixed delivery commitment. | AI3: Publish manufacturer documents only when public access and reuse are permitted; otherwise provide controlled access on request.
A4: =IF(B4=B3,A3,A3+1) -> 1 | B4: Thermal Analysis | C4: ThermCon Scientific | D4: Germany | E4: TC3500S Carbon Black Content Tester | F4: /products/thermal-analysis | G4: One page per product category | H4: 46257 | I4: TC3500S Carbon Black Content Tester | DIWAN Engineering & Technology Company | J4: tc3500s-carbon-black-content-tester | K4: The TC3500S automates carbon-black and ash-content testing for up to four samples with programmed gas switching, touchscreen operation and rapid furnace cooling. | L4: TC3500S Carbon Black Content Tester from ThermCon Scientific: key capabilities, technical specifications and applications. Request configuration advice and a quotation from DIWAN. | M4: Request technical information or a quote | N4: Draft complete - technical approval and assets pending | O4: The ThermCon Scientific TC3500S is a four-position carbon-black content tester designed for controlled heating, gas switching and automatic calculation of carbon-black and ash results. Its open-lid furnace design reduces cooling time between test stages. | P4: Four-sample capacity; one-click carbon-black and ash testing; automatic gas-path switching; 7-inch touchscreen; open-lid rapid-cooling structure; warning and result-printing functions. | Q4: Temperature range: room temperature to 1200°C; temperature sensitivity: 0.1°C; quartz tube: 44 × 600 mm; furnace zone: 45 × 300 mm; two gas paths; cooling from 900°C to room temperature in 20 minutes or less; power: AC 220V, 50/60Hz. | R4: Carbon-black and ash-content testing for polyethylene, polypropylene, cable materials, pipes, rubber compounds and related polymer products. | S4: https://www.thermconscientific.com/Resim/d7cdf5fbde_20255923322294.jpg | T4: TC3500S Carbon Black Content Tester from ThermCon Scientific | V4: No public downloadable brochure identified during review; provide documents on request after manufacturer rights and revision checks. | W4: TGA 1000 / 1600; STA 1000 / 1600; UL94 Flame Chamber | X4: Thermal Analysis enquiry → website group enquiry form → category owner assignment | Y4: TC3500S Carbon Black Content Tester, Thermal Analysis, ThermCon Scientific, laboratory instrument, DIWAN | Z4: https://www.thermconscientific.com/EN%2C119/tc3500s-carbon-black-content-tester.html | AA4: 46257 | AB4: Product Team / Technical Reviewer | AC4: =IF(AND(O4<>"",P4<>"",R4<>"",T4<>"",X4<>"",Y4<>"",Z4<>"",AA4<>"",AB4<>""),IF(AND(Q4<>"",S4<>"",U4<>""),"Ready for approval","Content drafted - assets/specs pending"),IF(COUNTA(O4:AB4)=0,"Not started","In progress")) -> Content drafted - assets/specs pending | AD4: Exact manufacturer product page verified; technical approval and publication assets remain required. Source reviewed 2026-08-23. Primary image and downloadable brochure assets remain open. | AG4: Availability, configuration and commercial supply are subject to confirmation by DIWAN and the manufacturer. | AH4: Lead time is confirmed in the formal quotation; do not publish a fixed delivery commitment. | AI4: Publish manufacturer documents only when public access and reuse are permitted; otherwise provide controlled access on request.
A5: =IF(B5=B4,A4,A4+1) -> 1 | B5: Thermal Analysis | C5: ThermCon Scientific | D5: Germany | E5: DTA 1000 / 1600 Differential Thermal Analyzer | F5: /products/thermal-analysis | G5: One page per product category | H5: 46257 | I5: DTA 1000 / 1600 Differential Thermal Analyzer | DIWAN Engineering & Technology Company | J5: dta-1000-1600-differential-thermal-analyzer | K5: The DTA 1000 / 1600 measures temperature differences between a sample and reference during programmed heating for phase-transition and reaction analysis at high temperature. | L5: DTA 1000 / 1600 Differential Thermal Analyzer from ThermCon Scientific: key capabilities, technical specifications and applications. Request configuration advice and a quotation from DIWAN. | M5: Request technical information or a quote | N5: Draft complete - technical approval and assets pending | O5: ThermCon Scientific's DTA 1000 / 1600 is a differential thermal analyzer with programmable temperature control, automatic atmosphere switching and real-time software analysis. The platform is designed for high-temperature studies where endothermic and exothermic events must be identified. | P5: ARM-based control; 7-inch color touchscreen; USB two-way communication; nickel-chromium sensor; programmable temperature control; automatic atmosphere switching; one-button calibration; live graph collection and analysis. | Q5: Temperature range: room temperature to 1250°C or 1550°C; signal range: 0 to ±2000 µV, expandable; sensitivity: 0.01 µV; heating rate: 0.1–100°C/min; temperature resolution: 0.01°C; temperature accuracy and repeatability: ±0.1°C. | R5: Ceramics, glass, minerals, metals, chemicals, catalysts and other materials requiring phase-transition, oxidation, decomposition or reaction-temperature analysis. | S5: https://www.thermconscientific.com/Resim/a05b35b702_2025585556764.jpg | T5: DTA 1000 / 1600 Differential Thermal Analyzer from ThermCon Scientific | V5: No public downloadable brochure identified during review; provide documents on request after manufacturer rights and revision checks. | W5: STA 1000 / 1600; TGA 1000 / 1600; DSC 600 | X5: Thermal Analysis enquiry → website group enquiry form → category owner assignment | Y5: DTA 1000 / 1600 Differential Thermal Analyzer, Thermal Analysis, ThermCon Scientific, laboratory instrument, DIWAN | Z5: https://www.thermconscientific.com/EN%2C121/dta-1000--1600-differential-thermal-analyzer.html | AA5: 46257 | AB5: Product Team / Technical Reviewer | AC5: =IF(AND(O5<>"",P5<>"",R5<>"",T5<>"",X5<>"",Y5<>"",Z5<>"",AA5<>"",AB5<>""),IF(AND(Q5<>"",S5<>"",U5<>""),"Ready for approval","Content drafted - assets/specs pending"),IF(COUNTA(O5:AB5)=0,"Not started","In progress")) -> Content drafted - assets/specs pending | AD5: Exact manufacturer product page verified; technical approval and publication assets remain required. Source reviewed 2026-08-23. Primary image and downloadable brochure assets remain open. | AG5: Availability, configuration and commercial supply are subject to confirmation by DIWAN and the manufacturer. | AH5: Lead time is confirmed in the formal quotation; do not publish a fixed delivery commitment. | AI5: Publish manufacturer documents only when public access and reuse are permitted; otherwise provide controlled access on request.
A6: =IF(B6=B5,A5,A5+1) -> 1 | B6: Thermal Analysis | C6: ThermCon Scientific | D6: Germany | E6: DSC 600 High-Precision Differential Scanning Calorimeter | F6: /products/thermal-analysis | G6: One page per product category | H6: 46257 | I6: DSC 600 High-Precision Differential Scanning Calorimeter | DIWAN Engineering & Technology Company | J6: dsc-600-high-precision-differential-scanning-calorimeter | K6: The DSC 600 is a high-precision differential scanning calorimeter for measuring melting, crystallization, glass transition, curing and oxidation-induction behavior. | L6: DSC 600 High-Precision Differential Scanning Calorimeter from ThermCon Scientific: key capabilities, technical specifications and applications. Request configuration advice and a quotation from DIWAN. | M6: Request technical information or a quote | N6: Draft complete - technical approval and assets pending | O6: The ThermCon Scientific DSC 600 measures heat-flow changes associated with physical and chemical transitions. Its high sensitivity, wide temperature options and touchscreen control support research, formulation work and routine quality control. | P6: High measurement sensitivity; stable baseline; strong repeatability; multiple cooling options; 7-inch touchscreen; programmable heating and cooling; three gas-control channels; real-time software analysis. | Q6: Temperature options extend from approximately -70°C to 600°C depending on configuration; sensitivity: 0.1 µW; noise: 0.001 mW; heating rate: 0.1–100°C/min; cooling rate: -0.1 to -60°C/min; three gas channels. | R6: Plastics, polymers, chemicals, food, pharmaceuticals, academic research, metrology and quality control; Tg, melting, crystallization, enthalpy, curing and OIT testing. | S6: https://www.thermconscientific.com/Resim/aa8f8e8e7d_2024324185816509.jpg | T6: DSC 600 High-Precision Differential Scanning Calorimeter from ThermCon Scientific | V6: No public downloadable brochure identified during review; provide documents on request after manufacturer rights and revision checks. | W6: DSC-600A; STA 1000 / 1600; TGA 1000 / 1600 | X6: Thermal Analysis enquiry → website group enquiry form → category owner assignment | Y6: DSC 600 High-Precision Differential Scanning Calorimeter, Thermal Analysis, ThermCon Scientific, laboratory instrument, DIWAN | Z6: https://www.thermconscientific.com/EN%2C24/dsc-600--high-precision-differential-scanning-calorimeter.html | AA6: 46257 | AB6: Product Team / Technical Reviewer | AC6: =IF(AND(O6<>"",P6<>"",R6<>"",T6<>"",X6<>"",Y6<>"",Z6<>"",AA6<>"",AB6<>""),IF(AND(Q6<>"",S6<>"",U6<>""),"Ready for approval","Content drafted - assets/specs pending"),IF(COUNTA(O6:AB6)=0,"Not started","In progress")) -> Content drafted - assets/specs pending | AD6: Exact manufacturer product page verified; configuration-specific temperature range must be confirmed during quotation. Source reviewed 2026-08-23. Primary image and downloadable brochure assets remain open. | AG6: Availability, configuration and commercial supply are subject to confirmation by DIWAN and the manufacturer. | AH6: Lead time is confirmed in the formal quotation; do not publish a fixed delivery commitment. | AI6: Publish manufacturer documents only when public access and reuse are permitted; otherwise provide controlled access on request.
A7: =IF(B7=B6,A6,A6+1) -> 1 | B7: Thermal Analysis | C7: ThermCon Scientific | D7: Germany | E7: DSC-600A Differential Scanning Calorimeter | F7: /products/thermal-analysis | G7: One page per product category | H7: 46257 | I7: DSC-600A Differential Scanning Calorimeter | DIWAN Engineering & Technology Company | J7: dsc-600a-differential-scanning-calorimeter | K7: The DSC-600A adds automated batch handling to DSC testing, allowing up to 40 samples to be processed with reduced operator intervention. | L7: DSC-600A Differential Scanning Calorimeter from ThermCon Scientific: key capabilities, technical specifications and applications. Request configuration advice and a quotation from DIWAN. | M7: Request technical information or a quote | N7: Draft complete - technical approval and assets pending | O7: The ThermCon Scientific DSC-600A is an automatic differential scanning calorimeter designed for repetitive laboratory workflows. A multi-position sample changer automates batch testing while retaining the DSC platform's transition, enthalpy, curing and oxidation-induction capabilities. | P7: Automatic sample changer for up to 40 samples; unattended batch testing; high-sensitivity DSC measurement; programmable temperature control; touchscreen operation; software-based data capture and analysis. | Q7: Automatic capacity: up to 40 samples; DSC functions and temperature configurations align with the DSC 600 platform and require final configuration confirmation; model-specific cooling and gas-control options are selected at quotation. | R7: High-throughput polymer, chemical, pharmaceutical, food and quality-control laboratories performing repetitive DSC measurements. | S7: https://www.thermconscientific.com/Resim/a637ae4c86_20255922813016.jpg | T7: DSC-600A Differential Scanning Calorimeter from ThermCon Scientific | V7: No public downloadable brochure identified during review; provide documents on request after manufacturer rights and revision checks. | W7: DSC 600; STA 1000 / 1600; TGA 1000 / 1600 | X7: Thermal Analysis enquiry → website group enquiry form → category owner assignment | Y7: DSC-600A Differential Scanning Calorimeter, Thermal Analysis, ThermCon Scientific, laboratory instrument, DIWAN | Z7: https://www.thermconscientific.com/EN%2C212/dsc---600a-differential-scanning-calorimeter.html | AA7: 46257 | AB7: Product Team / Technical Reviewer | AC7: =IF(AND(O7<>"",P7<>"",R7<>"",T7<>"",X7<>"",Y7<>"",Z7<>"",AA7<>"",AB7<>""),IF(AND(Q7<>"",S7<>"",U7<>""),"Ready for approval","Content drafted - assets/specs pending"),IF(COUNTA(O7:AB7)=0,"Not started","In progress")) -> Content drafted - assets/specs pending | AD7: Exact manufacturer product page verified; final technical configuration must be approved before publication. Source reviewed 2026-08-23. Primary image and downloadable brochure assets remain open. | AG7: Availability, configuration and commercial supply are subject to confirmation by DIWAN and the manufacturer. | AH7: Lead time is confirmed in the formal quotation; do not publish a fixed delivery commitment. | AI7: Publish manufacturer documents only when public access and reuse are permitted; otherwise provide controlled access on request.
A8: =IF(B8=B7,A7,A7+1) -> 2 | B8: Thermal Conductivity | C8: ThermCon Scientific | D8: Germany | E8: HFM50/300 Thermal Conductivity Tester | F8: /products/thermal-conductivity | G8: One page per product category | H8: 46257 | I8: HFM50/300 Thermal Conductivity Tester | DIWAN Engineering & Technology Company | J8: hfm50-300-thermal-conductivity-tester | K8: The HFM50/300 uses the heat-flow method to measure thermal conductivity, diffusivity and thermal resistance of small low- and medium-conductivity samples. | L8: HFM50/300 Thermal Conductivity Tester from ThermCon Scientific: key capabilities, technical specifications and applications. Request configuration advice and a quotation from DIWAN. | M8: Request technical information or a quote | N8: Draft complete - technical approval and assets pending | O8: ThermCon Scientific's HFM50/300 is a computer-controlled heat-flow instrument for compact samples, thin materials and interface products. Automatic plate positioning and thickness measurement simplify calibrated testing and data management. | P8: Automatic plate movement; automatic sample-thickness measurement; small-sample testing; multilayer thin-film method; programmable temperature control; stored calibration and test data; automatic analysis software. | Q8: Temperature options: room temperature to 40°C, 200°C or 300°C; sample: 30 mm diameter or 30 × 30 mm, thickness 0.1–20 mm; conductivity range: 0.010–45 W/m·K; thermal resistance: 0.000005–0.05 m²·K/W; accuracy: within ±3%; force: 0–500 N. | R8: Polymers, ceramics, insulation, composites, non-metallic materials, thermal interface pads, silicone grease and thin films; standards include ASTM E1530, ASTM C518, ISO 8301 and DIN EN 12667. | S8: https://www.thermconscientific.com/Resim/d6d050df5e_2024326131842234.jpg | T8: HFM50/300 Thermal Conductivity Tester from ThermCon Scientific | V8: No public downloadable brochure identified during review; provide documents on request after manufacturer rights and revision checks. | W8: HFM 300/600; HFM1600; THS 200; TPS 500 | X8: Thermal Conductivity enquiry → website group enquiry form → category owner assignment | Y8: HFM50/300 Thermal Conductivity Tester, Thermal Conductivity, ThermCon Scientific, laboratory instrument, DIWAN | Z8: https://www.thermconscientific.com/EN%2C33/hfm50300-thermal-conductivity-tester.html | AA8: 46257 | AB8: Product Team / Technical Reviewer | AC8: =IF(AND(O8<>"",P8<>"",R8<>"",T8<>"",X8<>"",Y8<>"",Z8<>"",AA8<>"",AB8<>""),IF(AND(Q8<>"",S8<>"",U8<>""),"Ready for approval","Content drafted - assets/specs pending"),IF(COUNTA(O8:AB8)=0,"Not started","In progress")) -> Content drafted - assets/specs pending | AD8: Exact manufacturer product page verified; technical approval and publication assets remain required. Source reviewed 2026-08-23. Primary image and downloadable brochure assets remain open. | AG8: Availability, configuration and commercial supply are subject to confirmation by DIWAN and the manufacturer. | AH8: Lead time is confirmed in the formal quotation; do not publish a fixed delivery commitment. | AI8: Publish manufacturer documents only when public access and reuse are permitted; otherwise provide controlled access on request.
A9: =IF(B9=B8,A8,A8+1) -> 2 | B9: Thermal Conductivity | C9: ThermCon Scientific | D9: Germany | E9: LFA 1600 Laser Flash Thermal Conductivity & Diffusivity Tester | F9: /products/thermal-conductivity | G9: One page per product category | H9: 46257 | I9: LFA 1600 Laser Flash Thermal Conductivity & Diffusivity Tester | DIWAN Engineering & Technology Company | J9: lfa-1600-laser-flash-thermal-conductivity-and-diffusivity-tester | K9: The LFA 1600 uses laser-flash heating and infrared detection to determine thermal diffusivity and calculate thermal conductivity across a broad material and temperature range. | L9: LFA 1600 Laser Flash Thermal Conductivity & Diffusivity Tester from ThermCon Scientific: key capabilities, technical specifications and applications. Request configuration advice and a quotation from DIWAN. | M9: Request technical information or a quote | N9: Draft complete - technical approval and assets pending | O9: The ThermCon Scientific LFA 1600 is a laser-flash thermal-property analyzer for rapid, non-contact measurement of thermal diffusivity. With density and heat-capacity inputs, the software supports thermal-conductivity calculation for high-performance materials. | P9: Laser-flash method; infrared temperature detection; high-temperature configurations; broad diffusivity and conductivity ranges; fast transient measurement; software calculation and reporting. | Q9: Temperature options: room temperature to 1000°C, 1400°C or 1600°C; sample diameter: 10–25 mm or square samples at least 10 × 10 mm; thickness: 0.1–10 mm; diffusivity: 0.01–1000 mm²/s; conductivity: 0.1–2000 W/m·K; accuracy: ±4%; repeatability: ±3%. | R9: Metals, alloys, diamond, ceramics, graphite, carbon fiber, plastics, polymers and composite materials for thermal-management and high-temperature research. | S9: https://www.thermconscientific.com/Resim/a161863b18_20244417457706.jpg | T9: LFA 1600 Laser Flash Thermal Conductivity & Diffusivity Tester from ThermCon Scientific | V9: No public downloadable brochure identified during review; provide documents on request after manufacturer rights and revision checks. | W9: HFM1600; HFM50/300; THS 200; TPS 500 | X9: Thermal Conductivity enquiry → website group enquiry form → category owner assignment | Y9: LFA 1600 Laser Flash Thermal Conductivity & Diffusivity Tester, Thermal Conductivity, ThermCon Scientific, laboratory instrument, DIWAN | Z9: https://www.thermconscientific.com/EN%2C34/lfa-1600-laser-flash-thermal-conductivity-diffusivity-tester.html | AA9: 46257 | AB9: Product Team / Technical Reviewer | AC9: =IF(AND(O9<>"",P9<>"",R9<>"",T9<>"",X9<>"",Y9<>"",Z9<>"",AA9<>"",AB9<>""),IF(AND(Q9<>"",S9<>"",U9<>""),"Ready for approval","Content drafted - assets/specs pending"),IF(COUNTA(O9:AB9)=0,"Not started","In progress")) -> Content drafted - assets/specs pending | AD9: Exact manufacturer URL verified. The product URL/title states LFA 1600, while part of the official page text references LFA 1000; confirm the model designation before publication. Source reviewed 2026-08-23. Primary image and downloadable brochure assets remain open. | AG9: Availability, configuration and commercial supply are subject to confirmation by DIWAN and the manufacturer. | AH9: Lead time is confirmed in the formal quotation; do not publish a fixed delivery commitment. | AI9: Publish manufacturer documents only when public access and reuse are permitted; otherwise provide controlled access on request.
A10: =IF(B10=B9,A9,A9+1) -> 2 | B10: Thermal Conductivity | C10: ThermCon Scientific | D10: Germany | E10: Tuber 200 Pipe Insulation Thermal Conductivity Tester | F10: /products/thermal-conductivity | G10: One page per product category | H10: 46257 | I10: Tuber 200 Pipe Insulation Thermal Conductivity Tester | DIWAN Engineering & Technology Company | J10: tuber-200-pipe-insulation-thermal-conductivity-tester | K10: The Tuber 200 measures thermal conductivity of cylindrical pipe-insulation systems using a guarded steady-state method for service temperatures up to 200°C. | L10: Tuber 200 Pipe Insulation Thermal Conductivity Tester from ThermCon Scientific: key capabilities, technical specifications and applications. Request configuration advice and a quotation from DIWAN. | M10: Request technical information or a quote | N10: Draft complete - technical approval and assets pending | O10: ThermCon Scientific's Tuber 200 is designed for pipe and tubular insulation where flat-sample instruments are not suitable. The system evaluates heat transfer through complete cylindrical insulation sections under controlled temperature conditions. | P10: Purpose-built cylindrical test geometry; steady-state heat-flow measurement; programmed temperature control; repeatable pipe-insulation testing; software-supported data acquisition. | Q10: Temperature range: room temperature to 200°C; accuracy: ±3%; repeatability: ±2%; temperature control: ±0.5°C; sample inner diameter: 18–89 mm; outer diameter: 50–249 mm; sample length: 500 mm; reference standards include ISO/DIS 8497 and GB 10296. | R10: Rubber and plastic pipe insulation, mineral and glass wool tubes, fiberglass pipe sections and industrial/building thermal-insulation systems. | S10: https://www.thermconscientific.com/Resim/8ffcfa83e7_2024441821136.jpg | T10: Tuber 200 Pipe Insulation Thermal Conductivity Tester from ThermCon Scientific | V10: No public downloadable brochure identified during review; provide documents on request after manufacturer rights and revision checks. | W10: HFM 300/600; HFM50/300; HFM1600 | X10: Thermal Conductivity enquiry → website group enquiry form → category owner assignment | Y10: Tuber 200 Pipe Insulation Thermal Conductivity Tester, Thermal Conductivity, ThermCon Scientific, laboratory instrument, DIWAN | Z10: https://www.thermconscientific.com/EN%2C36/tuber-200-pipe-insulation-thermal-conductivity-tester.html | AA10: 46257 | AB10: Product Team / Technical Reviewer | AC10: =IF(AND(O10<>"",P10<>"",R10<>"",T10<>"",X10<>"",Y10<>"",Z10<>"",AA10<>"",AB10<>""),IF(AND(Q10<>"",S10<>"",U10<>""),"Ready for approval","Content drafted - assets/specs pending"),IF(COUNTA(O10:AB10)=0,"Not started","In progress")) -> Content drafted - assets/specs pending | AD10: Exact manufacturer product page verified; technical approval and publication assets remain required. Source reviewed 2026-08-23. Primary image and downloadable brochure assets remain open. | AG10: Availability, configuration and commercial supply are subject to confirmation by DIWAN and the manufacturer. | AH10: Lead time is confirmed in the formal quotation; do not publish a fixed delivery commitment. | AI10: Publish manufacturer documents only when public access and reuse are permitted; otherwise provide controlled access on request.
A11: =IF(B11=B10,A10,A10+1) -> 2 | B11: Thermal Conductivity | C11: ThermCon Scientific | D11: Germany | E11: SB-850 Seebeck and Electrical Resistivity Test Device | F11: /products/thermal-conductivity | G11: One page per product category | H11: 46257 | I11: SB-850 Seebeck and Electrical Resistivity Test Device | DIWAN Engineering & Technology Company | J11: sb-850-seebeck-and-electrical-resistivity-test-device | K11: The SB-850 measures Seebeck coefficient and electrical resistivity of thermoelectric materials under controlled temperatures up to 850°C. | L11: SB-850 Seebeck and Electrical Resistivity Test Device from ThermCon Scientific: key capabilities, technical specifications and applications. Request configuration advice and a quotation from DIWAN. | M11: Request technical information or a quote | N11: Draft complete - technical approval and assets pending | O11: ThermCon Scientific's SB-850 combines Seebeck-coefficient and resistivity measurements for thermoelectric material development. The system applies controlled temperature gradients and current measurement to characterize metals and semiconductors. | P11: Combined Seebeck and resistivity testing; controlled high-temperature operation; programmable current; software acquisition; suitable for research-scale thermoelectric specimens. | Q11: Temperature range: room temperature to 850°C; temperature resolution: 0.001°C; control stability: ±0.25 K; current: 0–220 mA; Seebeck range: 0.5 µV/K–25 V/K; resistivity: 0.2 µΩ·mm–2.5 kΩ·mm; repeatability: ±3%; sample: 4 × 4 × 20 to 8 × 8 × 30 mm. | R11: Thermoelectric metals, alloys, semiconductors, energy-conversion materials and academic or industrial materials research. | S11: https://www.thermconscientific.com/Resim/0a26afe960_20244418445147.jpg | T11: SB-850 Seebeck and Electrical Resistivity Test Device from ThermCon Scientific | V11: No public downloadable brochure identified during review; provide documents on request after manufacturer rights and revision checks. | W11: LFA 1600; THS 200; TPS 500 | X11: Thermal Conductivity enquiry → website group enquiry form → category owner assignment | Y11: SB-850 Seebeck and Electrical Resistivity Test Device, Thermal Conductivity, ThermCon Scientific, laboratory instrument, DIWAN | Z11: https://www.thermconscientific.com/EN%2C37/sb-850-seebeck-and-electrical-resistivity-test-device.html | AA11: 46257 | AB11: Product Team / Technical Reviewer | AC11: =IF(AND(O11<>"",P11<>"",R11<>"",T11<>"",X11<>"",Y11<>"",Z11<>"",AA11<>"",AB11<>""),IF(AND(Q11<>"",S11<>"",U11<>""),"Ready for approval","Content drafted - assets/specs pending"),IF(COUNTA(O11:AB11)=0,"Not started","In progress")) -> Content drafted - assets/specs pending | AD11: Exact manufacturer product page verified; technical approval and publication assets remain required. Source reviewed 2026-08-23. Primary image and downloadable brochure assets remain open. | AG11: Availability, configuration and commercial supply are subject to confirmation by DIWAN and the manufacturer. | AH11: Lead time is confirmed in the formal quotation; do not publish a fixed delivery commitment. | AI11: Publish manufacturer documents only when public access and reuse are permitted; otherwise provide controlled access on request.
A12: =IF(B12=B11,A11,A11+1) -> 2 | B12: Thermal Conductivity | C12: ThermCon Scientific | D12: Germany | E12: THS 200 Thermal Conductivity Tester | F12: /products/thermal-conductivity | G12: One page per product category | H12: 46257 | I12: THS 200 Thermal Conductivity Tester | DIWAN Engineering & Technology Company | J12: ths-200-thermal-conductivity-tester | K12: The THS 200 is an automated transient hot-source instrument for rapid thermal-conductivity testing of solids, liquids, powders, pastes, films and insulation materials. | L12: THS 200 Thermal Conductivity Tester from ThermCon Scientific: key capabilities, technical specifications and applications. Request configuration advice and a quotation from DIWAN. | M12: Request technical information or a quote | N12: Draft complete - technical approval and assets pending | O12: The ThermCon Scientific THS 200 applies a transient heat source and monitors the resulting temperature response to calculate thermal conductivity. Automatic power adjustment, dual probes and software analysis support fast tests across diverse sample forms. | P12: Transient hot-source method; fully automatic comparison and power adjustment; dual high-precision probes; bidirectional software/device control; direct conductivity calculation; measurement in 160 seconds or less. | Q12: Conductivity range: 0.00001–50 W/m·K; temperature range: -30°C to 200°C; accuracy: 0.001 W/m·K; repeatability error: 1% or less; two probes; test time: 160 seconds or less; 18 ml holder for liquids and powders. | R12: Bulk solids, metals, liquids, powders, colloids, pastes, films, alloys, composites and thermal-insulation materials. | S12: https://www.thermconscientific.com/Resim/bb3630583e_202432613258124.jpg | T12: THS 200 Thermal Conductivity Tester from ThermCon Scientific | V12: No public downloadable brochure identified during review; provide documents on request after manufacturer rights and revision checks. | W12: TPS 500; HFM50/300; LFA 1600 | X12: Thermal Conductivity enquiry → website group enquiry form → category owner assignment | Y12: THS 200 Thermal Conductivity Tester, Thermal Conductivity, ThermCon Scientific, laboratory instrument, DIWAN | Z12: https://www.thermconscientific.com/EN%2C38/ths-200-thermal-conductivity-tester.html | AA12: 46257 | AB12: Product Team / Technical Reviewer | AC12: =IF(AND(O12<>"",P12<>"",R12<>"",T12<>"",X12<>"",Y12<>"",Z12<>"",AA12<>"",AB12<>""),IF(AND(Q12<>"",S12<>"",U12<>""),"Ready for approval","Content drafted - assets/specs pending"),IF(COUNTA(O12:AB12)=0,"Not started","In progress")) -> Content drafted - assets/specs pending | AD12: Exact manufacturer product page verified; technical approval and publication assets remain required. Source reviewed 2026-08-23. Primary image and downloadable brochure assets remain open. | AG12: Availability, configuration and commercial supply are subject to confirmation by DIWAN and the manufacturer. | AH12: Lead time is confirmed in the formal quotation; do not publish a fixed delivery commitment. | AI12: Publish manufacturer documents only when public access and reuse are permitted; otherwise provide controlled access on request.
A13: =IF(B13=B12,A12,A12+1) -> 2 | B13: Thermal Conductivity | C13: ThermCon Scientific | D13: Germany | E13: TPS 500 Thermal Conductivity Tester (Transient Plane Heat Source) | F13: /products/thermal-conductivity | G13: One page per product category | H13: 46257 | I13: TPS 500 Thermal Conductivity Tester (Transient Plane Heat Source) | DIWAN Engineering & Technology Company | J13: tps-500-thermal-conductivity-tester-transient-plane-heat-source | K13: The TPS 500 uses transient plane-source technology to measure thermal conductivity, diffusivity and heat capacity across solids, powders, films and coatings. | L13: TPS 500 Thermal Conductivity Tester (Transient Plane Heat Source) from ThermCon Scientific: key capabilities, technical specifications and applications. Request configuration advice and a quotation from DIWAN. | M13: Request technical information or a quote | N13: Draft complete - technical approval and assets pending | O13: ThermCon Scientific's TPS 500 is a flexible transient plane heat-source platform for rapid thermal-property measurement. Multiple probes and test modules support bulk, thin-film, anisotropic, single-sided and specific-heat workflows with minimal sample preparation. | P13: Transient plane-source method; fast testing in seconds; reduced sensitivity to contact resistance; minimal sample preparation; multiple test modules; automatic analysis and Excel export. | Q13: Conductivity range: 0.003–500 W/m·K; temperature options: room temperature to 40°C, 200°C or 1000°C; probe diameters: 7.5 mm and 15 mm; sample thickness: 0.05–10 mm; accuracy: ±5%; reproducibility: ±3%; USB data transfer. | R13: Metals, alloys, ceramics, ores, composites, silicon wafers, polymers, binders, paper, textiles, printed circuit boards, powders, films and coatings. | S13: https://www.thermconscientific.com/Resim/8c7535927c_202562492630719.jpg | T13: TPS 500 Thermal Conductivity Tester (Transient Plane Heat Source) from ThermCon Scientific | V13: No public downloadable brochure identified during review; provide documents on request after manufacturer rights and revision checks. | W13: THS 200; HFM50/300; LFA 1600; HFM 300/600 | X13: Thermal Conductivity enquiry → website group enquiry form → category owner assignment | Y13: TPS 500 Thermal Conductivity Tester (Transient Plane Heat Source), Thermal Conductivity, ThermCon Scientific, laboratory instrument, DIWAN | Z13: https://www.thermconscientific.com/EN%2C130/tps-500-thermal-conductivity-tester-transient-plane-heat-source.html | AA13: 46257 | AB13: Product Team / Technical Reviewer | AC13: =IF(AND(O13<>"",P13<>"",R13<>"",T13<>"",X13<>"",Y13<>"",Z13<>"",AA13<>"",AB13<>""),IF(AND(Q13<>"",S13<>"",U13<>""),"Ready for approval","Content drafted - assets/specs pending"),IF(COUNTA(O13:AB13)=0,"Not started","In progress")) -> Content drafted - assets/specs pending | AD13: Exact manufacturer product page verified; technical approval and publication assets remain required. Source reviewed 2026-08-23. Primary image and downloadable brochure assets remain open. | AG13: Availability, configuration and commercial supply are subject to confirmation by DIWAN and the manufacturer. | AH13: Lead time is confirmed in the formal quotation; do not publish a fixed delivery commitment. | AI13: Publish manufacturer documents only when public access and reuse are permitted; otherwise provide controlled access on request.
A14: =IF(B14=B13,A13,A13+1) -> 2 | B14: Thermal Conductivity | C14: ThermCon Scientific | D14: Germany | E14: HFM 300/600 Series Heat Flow Meter | F14: /products/thermal-conductivity | G14: One page per product category | H14: 46257 | I14: HFM 300/600 Series Heat Flow Meter | DIWAN Engineering & Technology Company | J14: hfm-300-600-series-heat-flow-meter | K14: The HFM 300/600 Series measures thermal conductivity and R-value of full-size insulation and building-material specimens using a calibrated heat-flow-meter method. | L14: HFM 300/600 Series Heat Flow Meter from ThermCon Scientific: key capabilities, technical specifications and applications. Request configuration advice and a quotation from DIWAN. | M14: Request technical information or a quote | N14: Draft complete - technical approval and assets pending | O14: ThermCon Scientific's HFM 300/600 Series is designed for larger insulation, construction and panel samples. Guarded plates, automatic thickness measurement and environmental compensation support repeatable conductivity and thermal-resistance testing. | P14: Large-format heat-flow-meter method; automatic sample-thickness measurement; guarded measurement area; controlled plate temperatures; calibration and compensation functions; automatic test and reporting software. | Q14: HFM 300 sample area: up to 300 × 300 mm with thickness 5–100 mm; HFM 600 sample area: up to 600 × 600 mm with thickness up to 200 mm; supports ASTM C518, ISO 8301, DIN EN 12667, EN 12664/12939 and related standards. | R14: EPS, XPS, PUR/PIR, mineral wool, rock wool, glass wool, ceramic fiber, vacuum panels, sandwich panels, fiberboard, concrete, drywall and composite building products. | S14: https://www.thermconscientific.com/Resim/122153bf0a_20252141426213.jpg | T14: HFM 300/600 Series Heat Flow Meter from ThermCon Scientific | V14: No public downloadable brochure identified during review; provide documents on request after manufacturer rights and revision checks. | W14: HFM50/300; Tuber 200; HFM1600 | X14: Thermal Conductivity enquiry → website group enquiry form → category owner assignment | Y14: HFM 300/600 Series Heat Flow Meter, Thermal Conductivity, ThermCon Scientific, laboratory instrument, DIWAN | Z14: https://www.thermconscientific.com/EN%2C221/hfm-300600-series-heat-flow-meter.html | AA14: 46257 | AB14: Product Team / Technical Reviewer | AC14: =IF(AND(O14<>"",P14<>"",R14<>"",T14<>"",X14<>"",Y14<>"",Z14<>"",AA14<>"",AB14<>""),IF(AND(Q14<>"",S14<>"",U14<>""),"Ready for approval","Content drafted - assets/specs pending"),IF(COUNTA(O14:AB14)=0,"Not started","In progress")) -> Content drafted - assets/specs pending | AD14: Exact manufacturer product page verified; confirm configuration-specific measurement range and plate-temperature options before publication. Source reviewed 2026-08-23. Primary image and downloadable brochure assets remain open. | AG14: Availability, configuration and commercial supply are subject to confirmation by DIWAN and the manufacturer. | AH14: Lead time is confirmed in the formal quotation; do not publish a fixed delivery commitment. | AI14: Publish manufacturer documents only when public access and reuse are permitted; otherwise provide controlled access on request.
... A17: =IF(B17=B16,A16,A16+1) -> 3 | B17: Dilatometry | C17: ThermCon Scientific | D17: Germany | E17: DIL Optical Sintering Point Tester (Optical Dilatometer) | F17: /products/dilatometry | G17: One page per product category | H17: 46257 | I17: DIL Optical Sintering Point Tester (Optical Dilatometer) | DIWAN Engineering & Technology Company | J17: dil-optical-sintering-point-tester-optical-dilatometer | K17: The DIL Optical uses high-temperature image analysis to measure sintering, softening, melting, refractoriness and contact-angle behavior without contacting the sample. | L17: DIL Optical Sintering Point Tester (Optical Dilatometer) from ThermCon Scientific: key capabilities, technical specifications and applications. Request configuration advice and a quotation from DIWAN. | M17: Request technical information or a quote | N17: Draft complete - technical approval and assets pending | O17: The ThermCon Scientific DIL Optical is a non-contact optical dilatometer and high-temperature microscopy system. A transmitted-image setup tracks specimen shape and dimensional change during heating, making it suitable for materials that soften, deform or melt. | P17: Non-contact optical measurement; high-temperature transmitted imaging; automated shape and dimensional analysis; programmable heating; software image capture; suitable for softening and melting materials. | Q17: Temperature range: approximately 30–1600°C; heating rate: 0.1–80°C/min; high-resolution optical imaging; nitrogen atmosphere and water-cooling provisions; sample dimensions and optical configuration require final confirmation. | R17: Sand, glass, compounds, refractories, ceramic raw materials and metals; sintering point, melting point, refractoriness, deformation and surface contact-angle studies. | S17: https://www.thermconscientific.com/Resim/93c33819fc_202443131745108.jpg | T17: DIL Optical Sintering Point Tester (Optical Dilatometer) from ThermCon Scientific | V17: No public downloadable brochure identified during review; provide documents on request after manufacturer rights and revision checks. | W17: DIL Series; DIL-D; DIL-C | X17: Dilatometry enquiry → website group enquiry form → category owner assignment | Y17: DIL Optical Sintering Point Tester (Optical Dilatometer), Dilatometry, ThermCon Scientific, laboratory instrument, DIWAN | Z17: https://www.thermconscientific.com/EN%2C109/dil-optical---sintering-point-tester-optical-dilatometer.html | AA17: 46257 | AB17: Product Team / Technical Reviewer | AC17: =IF(AND(O17<>"",P17<>"",R17<>"",T17<>"",X17<>"",Y17<>"",Z17<>"",AA17<>"",AB17<>""),IF(AND(Q17<>"",S17<>"",U17<>""),"Ready for approval","Content drafted - assets/specs pending"),IF(COUNTA(O17:AB17)=0,"Not started","In progress")) -> Content drafted - assets/specs pending | AD17: Exact manufacturer product page verified; confirm final optical specification and sample geometry before publication. Source reviewed 2026-08-23. Primary image and downloadable brochure assets remain open. | AG17: Availability, configuration and commercial supply are subject to confirmation by DIWAN and the manufacturer. | AH17: Lead time is confirmed in the formal quotation; do not publish a fixed delivery commitment. | AI17: Publish manufacturer documents only when public access and reuse are permitted; otherwise provide controlled access on request.
A18: =IF(B18=B17,A17,A17+1) -> 3 | B18: Dilatometry | C18: ThermCon Scientific | D18: Germany | E18: DIL-Q Quenching Deformation Dilatometer | F18: /products/dilatometry | G18: One page per product category | H18: 46257 | I18: DIL-Q Quenching Deformation Dilatometer | DIWAN Engineering & Technology Company | J18: dil-q-quenching-deformation-dilatometer | K18: The DIL-Q is ThermCon Scientific's quenching-deformation dilatometer line for studying dimensional change during controlled heating, cooling and quench cycles. | L18: DIL-Q Quenching Deformation Dilatometer from ThermCon Scientific: key capabilities, technical specifications and applications. Request configuration advice and a quotation from DIWAN. | M18: Request technical information or a quote | N18: Draft complete - technical approval and assets pending | O18: ThermCon Scientific lists the DIL-Q as a quenching deformation dilatometer within its dilatometry portfolio. The product is intended for temperature-dependent deformation and transformation studies where rapid cooling or quenching behavior is important. | P18: Quenching-deformation measurement; programmed thermal cycles; dimensional-change monitoring; application-specific atmosphere and cooling configuration subject to technical confirmation. | R18: Metals, alloys, heat-treatment research, phase-transformation studies and materials-development laboratories. | S18: https://www.thermconscientific.com/Resim/c2a83a2fe4_20244313181731.jpg | T18: DIL-Q Quenching Deformation Dilatometer from ThermCon Scientific | V18: No public downloadable brochure identified during review; provide documents on request after manufacturer rights and revision checks. | W18: DIL-D; DIL Series; DIL-C | X18: Dilatometry enquiry → website group enquiry form → category owner assignment | Y18: DIL-Q Quenching Deformation Dilatometer, Dilatometry, ThermCon Scientific, laboratory instrument, DIWAN | Z18: https://www.thermconscientific.com/EN%2C7/dilatometer.html | AA18: 46257 | AB18: Product Team / Technical Reviewer | AC18: =IF(AND(O18<>"",P18<>"",R18<>"",T18<>"",X18<>"",Y18<>"",Z18<>"",AA18<>"",AB18<>""),IF(AND(Q18<>"",S18<>"",U18<>""),"Ready for approval","Content drafted - assets/specs pending"),IF(COUNTA(O18:AB18)=0,"Not started","In progress")) -> Content drafted - assets/specs pending | AD18: Official manufacturer category listing verified, but a model-specific technical page was not reliably indexed. Temperature range, deformation range, quench rate, atmosphere and sample geometry require manufacturer confirmation. Source reviewed 2026-08-23. Primary image and downloadable brochure assets remain open. | AG18: Availability, configuration and commercial supply are subject to confirmation by DIWAN and the manufacturer. | AH18: Lead time is confirmed in the formal quotation; do not publish a fixed delivery commitment. | AI18: Publish manufacturer documents only when public access and reuse are permitted; otherwise provide controlled access on request.
A19: =IF(B19=B18,A18,A18+1) -> 3 | B19: Dilatometry | C19: ThermCon Scientific | D19: Germany | E19: DIL-D Series Thermal Expansion Dilatometer | F19: /products/dilatometry | G19: One page per product category | H19: 46257 | I19: DIL-D Series Thermal Expansion Dilatometer | DIWAN Engineering & Technology Company | J19: dil-d-series-thermal-expansion-dilatometer | K19: The DIL-D Series provides high-resolution thermal-expansion and deformation measurement with programmable heating and controlled cooling for advanced materials research. | L19: DIL-D Series Thermal Expansion Dilatometer from ThermCon Scientific: key capabilities, technical specifications and applications. Request configuration advice and a quotation from DIWAN. | M19: Request technical information or a quote | N19: Draft complete - technical approval and assets pending | O19: ThermCon Scientific's DIL-D Series is a research dilatometer for precision measurement of dimensional change during heating and cooling. The platform supports controlled atmosphere, optional vacuum and programmable force for thermal-expansion and transformation studies. | P19: High-resolution displacement measurement; programmable heating and cooling; air, inert-gas and optional vacuum operation; adjustable sample load; software control and reporting. | Q19: Temperature range: approximately 20–1400°C; heating rate: 0.1–100°C/min; cooling rate: 0.1–50°C/min; sample diameter: 4–10 mm; sample length: up to 25 or 50 mm; adjustable load: 0.01–1 N; displacement range options: ±2.5 or ±5 mm. | R19: Metals, ceramics, glass, polymers and composites; CTE, shrinkage, phase-transformation and thermal-cycle deformation studies. | S19: https://www.thermconscientific.com/Resim/28501d4c16_20255912498747.jpg | T19: DIL-D Series Thermal Expansion Dilatometer from ThermCon Scientific | V19: No public downloadable brochure identified during review; provide documents on request after manufacturer rights and revision checks. | W19: DIL Series; DIL-Q; DIL-C; DIL Optical | X19: Dilatometry enquiry → website group enquiry form → category owner assignment | Y19: DIL-D Series Thermal Expansion Dilatometer, Dilatometry, ThermCon Scientific, laboratory instrument, DIWAN | Z19: https://www.thermconscientific.com/EN%2C213/dil-d-series-thermal-expansion-dilatometer.html | AA19: 46257 | AB19: Product Team / Technical Reviewer | AC19: =IF(AND(O19<>"",P19<>"",R19<>"",T19<>"",X19<>"",Y19<>"",Z19<>"",AA19<>"",AB19<>""),IF(AND(Q19<>"",S19<>"",U19<>""),"Ready for approval","Content drafted - assets/specs pending"),IF(COUNTA(O19:AB19)=0,"Not started","In progress")) -> Content drafted - assets/specs pending | AD19: Exact manufacturer product page verified; confirm final configuration, cooling system and vacuum options before publication. Source reviewed 2026-08-23. Primary image and downloadable brochure assets remain open. | AG19: Availability, configuration and commercial supply are subject to confirmation by DIWAN and the manufacturer. | AH19: Lead time is confirmed in the formal quotation; do not publish a fixed delivery commitment. | AI19: Publish manufacturer documents only when public access and reuse are permitted; otherwise provide controlled access on request.
A20: =IF(B20=B19,A19,A19+1) -> 3 | B20: Dilatometry | C20: ThermCon Scientific | D20: Germany | E20: DIL-C Series Cryogenic Thermal Expansion Dilatometer | F20: /products/dilatometry | G20: One page per product category | H20: 46257 | I20: DIL-C Series Cryogenic Thermal Expansion Dilatometer | DIWAN Engineering & Technology Company | J20: dil-c-series-cryogenic-thermal-expansion-dilatometer | K20: The DIL-C is ThermCon Scientific's cryogenic thermal-expansion dilatometer line for measuring dimensional change below and above ambient temperature. | L20: DIL-C Series Cryogenic Thermal Expansion Dilatometer from ThermCon Scientific: key capabilities, technical specifications and applications. Request configuration advice and a quotation from DIWAN. | M20: Request technical information or a quote | N20: Draft complete - technical approval and assets pending | O20: ThermCon Scientific lists the DIL-C as a cryogenic thermal-expansion dilatometer within its dilatometry portfolio. It is intended for materials whose expansion or contraction must be characterized across sub-ambient thermal cycles. | P20: Cryogenic thermal-expansion testing; dimensional-change and CTE measurement; programmed low-temperature cycling; configuration-specific cooling and atmosphere controls require confirmation. | R20: Metals, polymers, composites, electronic materials and research applications requiring low-temperature expansion and contraction data. | S20: https://www.thermconscientific.com/Resim/2d20793701_20244313184672.jpg | T20: DIL-C Series Cryogenic Thermal Expansion Dilatometer from ThermCon Scientific | V20: No public downloadable brochure identified during review; provide documents on request after manufacturer rights and revision checks. | W20: DIL-D; DIL Series; DIL-Q | X20: Dilatometry enquiry → website group enquiry form → category owner assignment | Y20: DIL-C Series Cryogenic Thermal Expansion Dilatometer, Dilatometry, ThermCon Scientific, laboratory instrument, DIWAN | Z20: https://www.thermconscientific.com/EN%2C7/dilatometer.html | AA20: 46257 | AB20: Product Team / Technical Reviewer | AC20: =IF(AND(O20<>"",P20<>"",R20<>"",T20<>"",X20<>"",Y20<>"",Z20<>"",AA20<>"",AB20<>""),IF(AND(Q20<>"",S20<>"",U20<>""),"Ready for approval","Content drafted - assets/specs pending"),IF(COUNTA(O20:AB20)=0,"Not started","In progress")) -> Content drafted - assets/specs pending | AD20: Official manufacturer category listing verified, but a model-specific technical page was not reliably indexed. Temperature range, cooling method, displacement resolution and sample geometry require manufacturer confirmation. Source reviewed 2026-08-23. Primary image and downloadable brochure assets remain open. | AG20: Availability, configuration and commercial supply are subject to confirmation by DIWAN and the manufacturer. | AH20: Lead time is confirmed in the formal quotation; do not publish a fixed delivery commitment. | AI20: Publish manufacturer documents only when public access and reuse are permitted; otherwise provide controlled access on request.
A21: =IF(B21=B20,A20,A20+1) -> 4 | B21: Material Testing | C21: ThermCon Scientific | D21: Germany | E21: CRUMPLEFLEX Fabric Flexing Tester | F21: /products/material-testing | G21: One page per product category | H21: 46257 | I21: CRUMPLEFLEX Fabric Flexing Tester | DIWAN Engineering & Technology Company | J21: crumpleflex-fabric-flexing-tester | K21: The CRUMPLEFLEX is listed by ThermCon Scientific as a fabric flexing tester for evaluating material durability under repeated crumpling or flexing cycles. | L21: CRUMPLEFLEX Fabric Flexing Tester from ThermCon Scientific: key capabilities, technical specifications and applications. Request configuration advice and a quotation from DIWAN. | M21: Request technical information or a quote | N21: Draft complete - technical approval and assets pending | O21: ThermCon Scientific presents CRUMPLEFLEX as a fabric flexing tester within its materials-testing content. The system is intended to assess how flexible sheet or fabric materials withstand repeated mechanical deformation. | P21: Repeated flexing or crumpling assessment; laboratory durability screening; method and fixture configuration require technical confirmation. | R21: Textiles, coated fabrics, flexible composites and sheet materials requiring comparative flex-durability testing. | T21: CRUMPLEFLEX Fabric Flexing Tester from ThermCon Scientific | V21: No public downloadable brochure identified during review; provide documents on request after manufacturer rights and revision checks. | W21: UL94 Horizontal/Vertical Flame Chamber | X21: Material Testing enquiry → website group enquiry form → category owner assignment | Y21: CRUMPLEFLEX Fabric Flexing Tester, Material Testing, ThermCon Scientific, laboratory instrument, DIWAN | Z21: https://www.thermconscientific.com/ | AA21: 46257 | AB21: Product Team / Technical Reviewer | AC21: =IF(AND(O21<>"",P21<>"",R21<>"",T21<>"",X21<>"",Y21<>"",Z21<>"",AA21<>"",AB21<>""),IF(AND(Q21<>"",S21<>"",U21<>""),"Ready for approval","Content drafted - assets/specs pending"),IF(COUNTA(O21:AB21)=0,"Not started","In progress")) -> Content drafted - assets/specs pending | AD21: Only the official manufacturer homepage/video listing was verified. Test method, standards, speed, stroke, specimen size and pass/fail criteria require manufacturer confirmation before a product page is published. Source reviewed 2026-08-23. Primary image and downloadable brochure assets remain open. | AG21: Availability, configuration and commercial supply are subject to confirmation by DIWAN and the manufacturer. | AH21: Lead time is confirmed in the formal quotation; do not publish a fixed delivery commitment. | AI21: Publish manufacturer documents only when public access and reuse are permitted; otherwise provide controlled access on request.
A22: =IF(B22=B21,A21,A21+1) -> 4 | B22: Material Testing | C22: ThermCon Scientific | D22: Germany | E22: UL94 Horizontal/Vertical Flame Chamber | F22: /products/material-testing | G22: One page per product category | H22: 46257 | I22: UL94 Horizontal/Vertical Flame Chamber | DIWAN Engineering & Technology Company | J22: ul94-horizontal-vertical-flame-chamber | K22: The UL94 Horizontal/Vertical Flame Chamber is an automated system for evaluating the flammability and flame-retardant behavior of plastic materials in horizontal and vertical orientations. | L22: UL94 Horizontal/Vertical Flame Chamber from ThermCon Scientific: key capabilities, technical specifications and applications. Request configuration advice and a quotation from DIWAN. | M22: Request technical information or a quote | N22: Draft complete - technical approval and assets pending | O22: ThermCon Scientific's UL94 Horizontal/Vertical Flame Chamber supports controlled flame testing of plastic specimens. Touchscreen operation and automated test control are intended to improve consistency for horizontal and vertical burning assessments. | P22: Horizontal and vertical flame testing; UL 94-oriented test workflow; smart touchscreen control; automated and user-friendly operation; precision flame application. | Q22: Manufacturer confirms horizontal and vertical testing with touchscreen control; chamber dimensions, burner specification, gas requirements, timer resolution and supported UL 94 classifications require technical confirmation. | R22: Plastic materials, polymer components, electrical and electronic products, appliance materials and quality-control laboratories performing flammability screening. | T22: UL94 Horizontal/Vertical Flame Chamber from ThermCon Scientific | V22: No public downloadable brochure identified during review; provide documents on request after manufacturer rights and revision checks. | W22: TC3500S Carbon Black Content Tester | X22: Material Testing enquiry → website group enquiry form → category owner assignment | Y22: UL94 Horizontal/Vertical Flame Chamber, Material Testing, ThermCon Scientific, laboratory instrument, DIWAN | Z22: https://www.thermconscientific.com/ | AA22: 46257 | AB22: Product Team / Technical Reviewer | AC22: =IF(AND(O22<>"",P22<>"",R22<>"",T22<>"",X22<>"",Y22<>"",Z22<>"",AA22<>"",AB22<>""),IF(AND(Q22<>"",S22<>"",U22<>""),"Ready for approval","Content drafted - assets/specs pending"),IF(COUNTA(O22:AB22)=0,"Not started","In progress")) -> Content drafted - assets/specs pending | AD22: Official manufacturer homepage product feature verified. A dedicated indexed product page and complete technical specification must be confirmed before publication. Source reviewed 2026-08-23. Primary image and downloadable brochure assets remain open. | AG22: Availability, configuration and commercial supply are subject to confirmation by DIWAN and the manufacturer. | AH22: Lead time is confirmed in the formal quotation; do not publish a fixed delivery commitment. | AI22: Publish manufacturer documents only when public access and reuse are permitted; otherwise provide controlled access on request.
A23: =IF(B23=B22,A22,A22+1) -> 5 | B23: Analyzers | C23: Young In Chromass | D23: South Korea | E23: Gas Analyzer | F23: /products/analyzers | G23: One page per product category | H23: 46257 | I23: Gas Analyzer | DIWAN Engineering & Technology Company | J23: gas-analyzer | K23: =E23&" is "&IF(ISNUMBER(SEARCH(LEFT(LOWER(B23),1),"aeiou")),"an ","a ")&LOWER(B23)&" product from "&C23&" for application-specific laboratory, engineering or industrial use." -> Gas Analyzer is an analyzers product from Young In Chromass for application-specific laboratory, engineering or industrial use. | L23: =E23&" from "&C23&" for "&LOWER(B23)&" applications. Review configuration requirements and request technical information or a quotation from DIWAN." -> Gas Analyzer from Young In Chromass for analyzers applications. Review configuration requirements and request technical information or a quotation from DIWAN. | M23: Request technical information or a quote | N23: Baseline definition complete - official specifications and assets pending | O23: {=_xlfn.LET(_xlpm.n,LOWER(E23),_xlpm.c,LOWER(B23),_xlpm.t,_xlfn.IFS(OR(ISNUMBER(SEARCH("lens",_xlpm.n)),ISNUMBER(SEARCH("optic",_xlpm.n)),ISNUMBER(SEARCH("polarizer",_xlpm.n))),"precision optical component",OR(ISNUMBER(SEARCH("camera",_xlpm.n)),ISNUMBER(SEARCH("imaging",_xlpm.n))),"scientific or industrial imaging system",ISNUMBER(SEARCH("pump",_xlpm.n)),"precision fluid-delivery system",OR(ISNUMBER(SEARCH("reactor",_xlpm.n)),ISNUMBER(SEARCH("autoclave",_xlpm.n)),ISNUMBER(SEARCH("pilot",_xlpm.n))),"laboratory or pilot-process system",OR(ISNUMBER(SEARCH("analyzer",_xlpm.n)),ISNUMBER(SEARCH("spectrometer",_xlpm.n)),ISNUMBER(SEARCH("hplc",_xlpm.n)),ISNUMBER(SEARCH("chrom",_xlpm.n))),"analytical laboratory instrument",OR(ISNUMBER(SEARCH("tester",_xlpm.n)),ISNUMBER(SEARCH("testing machine",_xlpm.n)),ISNUMBER(SEARCH("chamber",_xlpm.n))),"materials or component testing system",OR(ISNUMBER(SEARCH("sensor",_xlpm.n)),ISNUMBER(SEARCH("terminal",_xlpm.n)),ISNUMBER(SEARCH("station",_xlpm.n)),ISNUMBER(SEARCH("satellite",_xlpm.n))),"space or sensing subsystem",ISNUMBER(SEARCH("software",_xlpm.n)),"specialized engineering software platform",TRUE,"specialized "&_xlpm.c&" product"),_xlpm.art,IF(ISNUMBER(SEARCH(LEFT(_xlpm.t,1),"aeiou")),"an ","a "),E23&" is "&_xlpm.art&_xlpm.t&" from "&C23&" designed for application-specific laboratory, engineering or industrial use. It belongs to DIWAN's "&B23&" portfolio; final configuration must be selected against performance, integration and compliance requirements.")} -> Gas Analyzer is an analytical laboratory instrument from Young In Chromass designed for application-specific laboratory, engineering or industrial use. It belongs to DIWAN's Analyzers portfolio; final configuration must be selected against performance, integration and compliance requirements. | P23: ="Selection should confirm the model-specific operating range, capacity, accuracy, interfaces, utilities, accessories, standards, environmental limits and service requirements. Final capabilities depend on the approved "&E23&" configuration." -> Selection should confirm the model-specific operating range, capacity, accuracy, interfaces, utilities, accessories, standards, environmental limits and service requirements. Final capabilities depend on the approved Gas Analyzer configuration. | R23: =B23&" applications; laboratory research, engineering development, quality control and industrial deployment where applicable. Suitability must be confirmed against the user's sample, process, environment and required standards." -> Analyzers applications; laboratory research, engineering development, quality control and industrial deployment where applicable. Suitability must be confirmed against the user's sample, process, environment and required standards. | T23: =E23&" from "&C23 -> Gas Analyzer from Young In Chromass | V23: No public downloadable document captured yet; provide the latest approved manufacturer document on request after revision and reuse checks. | W23: ="See other "&B23&" products" -> See other Analyzers products | X23: =B23&" enquiry → website group enquiry form → category owner assignment" -> Analyzers enquiry → website group enquiry form → category owner assignment | Y23: =E23&", "&B23&", "&C23&", technical equipment, DIWAN" -> Gas Analyzer, Analyzers, Young In Chromass, technical equipment, DIWAN | Z23: https://eng.youngincm.com/goods/list.php?M2_IDX=18659 | AA23: 46257 | AB23: Product Team / Technical Reviewer | AC23: =IF(AND(O23<>"",P23<>"",R23<>"",T23<>"",X23<>"",Y23<>"",Z23<>"",AA23<>"",AB23<>""),IF(AND(Q23<>"",S23<>"",U23<>""),"Ready for approval","Content drafted - assets/specs pending"),IF(COUNTA(O23:AB23)=0,"Not started","In progress")) -> Content drafted - assets/specs pending | AD23: ="Baseline definition created from the official catalog name, partner and category classification ("&G23&"). Model-specific specifications, images and downloadable documents must be extracted from the linked official source and technically approved before publication. Source register reviewed 2026-08-23." -> Baseline definition created from the official catalog name, partner and category classification (One page per product category). Model-specific specifications, images and downloadable documents must be extracted from the linked official source and technically approved before publication. Source register reviewed 2026-08-23. | AG23: Availability, configuration and commercial supply are subject to confirmation by DIWAN and the manufacturer. | AH23: Lead time is confirmed in the formal quotation; do not publish a fixed delivery commitment. | AI23: Publish manufacturer documents only when public access and reuse are permitted; otherwise provide controlled access on request.
A24: =IF(B24=B23,A23,A23+1) -> 5 | B24: Analyzers | C24: Young In Chromass | D24: South Korea | E24: Hand Sanitizer Analyzer | F24: /products/analyzers | G24: One page per product category | H24: 46257 | I24: Hand Sanitizer Analyzer | DIWAN Engineering & Technology Company | J24: hand-sanitizer-analyzer | K24: =E24&" is "&IF(ISNUMBER(SEARCH(LEFT(LOWER(B24),1),"aeiou")),"an ","a ")&LOWER(B24)&" product from "&C24&" for application-specific laboratory, engineering or industrial use." -> Hand Sanitizer Analyzer is an analyzers product from Young In Chromass for application-specific laboratory, engineering or industrial use. | L24: =E24&" from "&C24&" for "&LOWER(B24)&" applications. Review configuration requirements and request technical information or a quotation from DIWAN." -> Hand Sanitizer Analyzer from Young In Chromass for analyzers applications. Review configuration requirements and request technical information or a quotation from DIWAN. | M24: Request technical information or a quote | N24: Baseline definition complete - official specifications and assets pending | O24: {=_xlfn.LET(_xlpm.n,LOWER(E24),_xlpm.c,LOWER(B24),_xlpm.t,_xlfn.IFS(OR(ISNUMBER(SEARCH("lens",_xlpm.n)),ISNUMBER(SEARCH("optic",_xlpm.n)),ISNUMBER(SEARCH("polarizer",_xlpm.n))),"precision optical component",OR(ISNUMBER(SEARCH("camera",_xlpm.n)),ISNUMBER(SEARCH("imaging",_xlpm.n))),"scientific or industrial imaging system",ISNUMBER(SEARCH("pump",_xlpm.n)),"precision fluid-delivery system",OR(ISNUMBER(SEARCH("reactor",_xlpm.n)),ISNUMBER(SEARCH("autoclave",_xlpm.n)),ISNUMBER(SEARCH("pilot",_xlpm.n))),"laboratory or pilot-process system",OR(ISNUMBER(SEARCH("analyzer",_xlpm.n)),ISNUMBER(SEARCH("spectrometer",_xlpm.n)),ISNUMBER(SEARCH("hplc",_xlpm.n)),ISNUMBER(SEARCH("chrom",_xlpm.n))),"analytical laboratory instrument",OR(ISNUMBER(SEARCH("tester",_xlpm.n)),ISNUMBER(SEARCH("testing machine",_xlpm.n)),ISNUMBER(SEARCH("chamber",_xlpm.n))),"materials or component testing system",OR(ISNUMBER(SEARCH("sensor",_xlpm.n)),ISNUMBER(SEARCH("terminal",_xlpm.n)),ISNUMBER(SEARCH("station",_xlpm.n)),ISNUMBER(SEARCH("satellite",_xlpm.n))),"space or sensing subsystem",ISNUMBER(SEARCH("software",_xlpm.n)),"specialized engineering software platform",TRUE,"specialized "&_xlpm.c&" product"),_xlpm.art,IF(ISNUMBER(SEARCH(LEFT(_xlpm.t,1),"aeiou")),"an ","a "),E24&" is "&_xlpm.art&_xlpm.t&" from "&C24&" designed for application-specific laboratory, engineering or industrial use. It belongs to DIWAN's "&B24&" portfolio; final configuration must be selected against performance, integration and compliance requirements.")} -> Hand Sanitizer Analyzer is an analytical laboratory instrument from Young In Chromass designed for application-specific laboratory, engineering or industrial use. It belongs to DIWAN's Analyzers portfolio; final configuration must be selected against performance, integration and compliance requirements. | P24: ="Selection should confirm the model-specific operating range, capacity, accuracy, interfaces, utilities, accessories, standards, environmental limits and service requirements. Final capabilities depend on the approved "&E24&" configuration." -> Selection should confirm the model-specific operating range, capacity, accuracy, interfaces, utilities, accessories, standards, environmental limits and service requirements. Final capabilities depend on the approved Hand Sanitizer Analyzer configuration. | R24: =B24&" applications; laboratory research, engineering development, quality control and industrial deployment where applicable. Suitability must be confirmed against the user's sample, process, environment and required standards." -> Analyzers applications; laboratory research, engineering development, quality control and industrial deployment where applicable. Suitability must be confirmed against the user's sample, process, environment and required standards. | T24: =E24&" from "&C24 -> Hand Sanitizer Analyzer from Young In Chromass | V24: No public downloadable document captured yet; provide the latest approved manufacturer document on request after revision and reuse checks. | W24: ="See other "&B24&" products" -> See other Analyzers products | X24: =B24&" enquiry → website group enquiry form → category owner assignment" -> Analyzers enquiry → website group enquiry form → category owner assignment | Y24: =E24&", "&B24&", "&C24&", technical equipment, DIWAN" -> Hand Sanitizer Analyzer, Analyzers, Young In Chromass, technical equipment, DIWAN | Z24: https://eng.youngincm.com/goods/list.php?M2_IDX=18659 | AA24: 46257 | AB24: Product Team / Technical Reviewer | AC24: =IF(AND(O24<>"",P24<>"",R24<>"",T24<>"",X24<>"",Y24<>"",Z24<>"",AA24<>"",AB24<>""),IF(AND(Q24<>"",S24<>"",U24<>""),"Ready for approval","Content drafted - assets/specs pending"),IF(COUNTA(O24:AB24)=0,"Not started","In progress")) -> Content drafted - assets/specs pending | AD24: ="Baseline definition created from the official catalog name, partner and category classification ("&G24&"). Model-specific specifications, images and downloadable documents must be extracted from the linked official source and technically approved before publication. Source register reviewed 2026-08-23." -> Baseline definition created from the official catalog name, partner and category classification (One page per product category). Model-specific specifications, images and downloadable documents must be extracted from the linked official source and technically approved before publication. Source register reviewed 2026-08-23. | AG24: Availability, configuration and commercial supply are subject to confirmation by DIWAN and the manufacturer. | AH24: Lead time is confirmed in the formal quotation; do not publish a fixed delivery commitment. | AI24: Publish manufacturer documents only when public access and reuse are permitted; otherwise provide controlled access on request.
A25: =IF(B25=B24,A24,A24+1) -> 5 | B25: Analyzers | C25: Young In Chromass | D25: South Korea | E25: ChroZen ASTM D4815 Player | F25: /products/analyzers | G25: One page per product category | H25: 46257 | I25: ChroZen ASTM D4815 Player | DIWAN Engineering & Technology Company | J25: chrozen-astm-d4815-player | K25: =E25&" is "&IF(ISNUMBER(SEARCH(LEFT(LOWER(B25),1),"aeiou")),"an ","a ")&LOWER(B25)&" product from "&C25&" for application-specific laboratory, engineering or industrial use." -> ChroZen ASTM D4815 Player is an analyzers product from Young In Chromass for application-specific laboratory, engineering or industrial use. | L25: =E25&" from "&C25&" for "&LOWER(B25)&" applications. Review configuration requirements and request technical information or a quotation from DIWAN." -> ChroZen ASTM D4815 Player from Young In Chromass for analyzers applications. Review configuration requirements and request technical information or a quotation from DIWAN. | M25: Request technical information or a quote | N25: Baseline definition complete - official specifications and assets pending | O25: {=_xlfn.LET(_xlpm.n,LOWER(E25),_xlpm.c,LOWER(B25),_xlpm.t,_xlfn.IFS(OR(ISNUMBER(SEARCH("lens",_xlpm.n)),ISNUMBER(SEARCH("optic",_xlpm.n)),ISNUMBER(SEARCH("polarizer",_xlpm.n))),"precision optical component",OR(ISNUMBER(SEARCH("camera",_xlpm.n)),ISNUMBER(SEARCH("imaging",_xlpm.n))),"scientific or industrial imaging system",ISNUMBER(SEARCH("pump",_xlpm.n)),"precision fluid-delivery system",OR(ISNUMBER(SEARCH("reactor",_xlpm.n)),ISNUMBER(SEARCH("autoclave",_xlpm.n)),ISNUMBER(SEARCH("pilot",_xlpm.n))),"laboratory or pilot-process system",OR(ISNUMBER(SEARCH("analyzer",_xlpm.n)),ISNUMBER(SEARCH("spectrometer",_xlpm.n)),ISNUMBER(SEARCH("hplc",_xlpm.n)),ISNUMBER(SEARCH("chrom",_xlpm.n))),"analytical laboratory instrument",OR(ISNUMBER(SEARCH("tester",_xlpm.n)),ISNUMBER(SEARCH("testing machine",_xlpm.n)),ISNUMBER(SEARCH("chamber",_xlpm.n))),"materials or component testing system",OR(ISNUMBER(SEARCH("sensor",_xlpm.n)),ISNUMBER(SEARCH("terminal",_xlpm.n)),ISNUMBER(SEARCH("station",_xlpm.n)),ISNUMBER(SEARCH("satellite",_xlpm.n))),"space or sensing subsystem",ISNUMBER(SEARCH("software",_xlpm.n)),"specialized engineering software platform",TRUE,"specialized "&_xlpm.c&" product"),_xlpm.art,IF(ISNUMBER(SEARCH(LEFT(_xlpm.t,1),"aeiou")),"an ","a "),E25&" is "&_xlpm.art&_xlpm.t&" from "&C25&" designed for application-specific laboratory, engineering or industrial use. It belongs to DIWAN's "&B25&" portfolio; final configuration must be selected against performance, integration and compliance requirements.")} -> ChroZen ASTM D4815 Player is a specialized analyzers product from Young In Chromass designed for application-specific laboratory, engineering or industrial use. It belongs to DIWAN's Analyzers portfolio; final configuration must be selected against performance, integration and compliance requirements. | P25: ="Selection should confirm the model-specific operating range, capacity, accuracy, interfaces, utilities, accessories, standards, environmental limits and service requirements. Final capabilities depend on the approved "&E25&" configuration." -> Selection should confirm the model-specific operating range, capacity, accuracy, interfaces, utilities, accessories, standards, environmental limits and service requirements. Final capabilities depend on the approved ChroZen ASTM D4815 Player configuration. | R25: =B25&" applications; laboratory research, engineering development, quality control and industrial deployment where applicable. Suitability must be confirmed against the user's sample, process, environment and required standards." -> Analyzers applications; laboratory research, engineering development, quality control and industrial deployment where applicable. Suitability must be confirmed against the user's sample, process, environment and required standards. | T25: =E25&" from "&C25 -> ChroZen ASTM D4815 Player from Young In Chromass | V25: No public downloadable document captured yet; provide the latest approved manufacturer document on request after revision and reuse checks. | W25: ="See other "&B25&" products" -> See other Analyzers products | X25: =B25&" enquiry → website group enquiry form → category owner assignment" -> Analyzers enquiry → website group enquiry form → category owner assignment | Y25: =E25&", "&B25&", "&C25&", technical equipment, DIWAN" -> ChroZen ASTM D4815 Player, Analyzers, Young In Chromass, technical equipment, DIWAN | Z25: https://eng.youngincm.com/goods/list.php?M2_IDX=18659 | AA25: 46257 | AB25: Product Team / Technical Reviewer | AC25: =IF(AND(O25<>"",P25<>"",R25<>"",T25<>"",X25<>"",Y25<>"",Z25<>"",AA25<>"",AB25<>""),IF(AND(Q25<>"",S25<>"",U25<>""),"Ready for approval","Content drafted - assets/specs pending"),IF(COUNTA(O25:AB25)=0,"Not started","In progress")) -> Content drafted - assets/specs pending | AD25: ="Baseline definition created from the official catalog name, partner and category classification ("&G25&"). Model-specific specifications, images and downloadable documents must be extracted from the linked official source and technically approved before publication. Source register reviewed 2026-08-23." -> Baseline definition created from the official catalog name, partner and category classification (One page per product category). Model-specific specifications, images and downloadable documents must be extracted from the linked official source and technically approved before publication. Source register reviewed 2026-08-23. | AG25: Availability, configuration and commercial supply are subject to confirmation by DIWAN and the manufacturer. | AH25: Lead time is confirmed in the formal quotation; do not publish a fixed delivery commitment. | AI25: Publish manufacturer documents only when public access and reuse are permitted; otherwise provide controlled access on request.
A26: =IF(B26=B25,A25,A25+1) -> 5 | B26: Analyzers | C26: Young In Chromass | D26: South Korea | E26: ChroZen ASTM D5580 Player | F26: /products/analyzers | G26: One page per product category | H26: 46257 | I26: ChroZen ASTM D5580 Player | DIWAN Engineering & Technology Company | J26: chrozen-astm-d5580-player | K26: =E26&" is "&IF(ISNUMBER(SEARCH(LEFT(LOWER(B26),1),"aeiou")),"an ","a ")&LOWER(B26)&" product from "&C26&" for application-specific laboratory, engineering or industrial use." -> ChroZen ASTM D5580 Player is an analyzers product from Young In Chromass for application-specific laboratory, engineering or industrial use. | L26: =E26&" from "&C26&" for "&LOWER(B26)&" applications. Review configuration requirements and request technical information or a quotation from DIWAN." -> ChroZen ASTM D5580 Player from Young In Chromass for analyzers applications. Review configuration requirements and request technical information or a quotation from DIWAN. | M26: Request technical information or a quote | N26: Baseline definition complete - official specifications and assets pending | O26: {=_xlfn.LET(_xlpm.n,LOWER(E26),_xlpm.c,LOWER(B26),_xlpm.t,_xlfn.IFS(OR(ISNUMBER(SEARCH("lens",_xlpm.n)),ISNUMBER(SEARCH("optic",_xlpm.n)),ISNUMBER(SEARCH("polarizer",_xlpm.n))),"precision optical component",OR(ISNUMBER(SEARCH("camera",_xlpm.n)),ISNUMBER(SEARCH("imaging",_xlpm.n))),"scientific or industrial imaging system",ISNUMBER(SEARCH("pump",_xlpm.n)),"precision fluid-delivery system",OR(ISNUMBER(SEARCH("reactor",_xlpm.n)),ISNUMBER(SEARCH("autoclave",_xlpm.n)),ISNUMBER(SEARCH("pilot",_xlpm.n))),"laboratory or pilot-process system",OR(ISNUMBER(SEARCH("analyzer",_xlpm.n)),ISNUMBER(SEARCH("spectrometer",_xlpm.n)),ISNUMBER(SEARCH("hplc",_xlpm.n)),ISNUMBER(SEARCH("chrom",_xlpm.n))),"analytical laboratory instrument",OR(ISNUMBER(SEARCH("tester",_xlpm.n)),ISNUMBER(SEARCH("testing machine",_xlpm.n)),ISNUMBER(SEARCH("chamber",_xlpm.n))),"materials or component testing system",OR(ISNUMBER(SEARCH("sensor",_xlpm.n)),ISNUMBER(SEARCH("terminal",_xlpm.n)),ISNUMBER(SEARCH("station",_xlpm.n)),ISNUMBER(SEARCH("satellite",_xlpm.n))),"space or sensing subsystem",ISNUMBER(SEARCH("software",_xlpm.n)),"specialized engineering software platform",TRUE,"specialized "&_xlpm.c&" product"),_xlpm.art,IF(ISNUMBER(SEARCH(LEFT(_xlpm.t,1),"aeiou")),"an ","a "),E26&" is "&_xlpm.art&_xlpm.t&" from "&C26&" designed for application-specific laboratory, engineering or industrial use. It belongs to DIWAN's "&B26&" portfolio; final configuration must be selected against performance, integration and compliance requirements.")} -> ChroZen ASTM D5580 Player is a specialized analyzers product from Young In Chromass designed for application-specific laboratory, engineering or industrial use. It belongs to DIWAN's Analyzers portfolio; final configuration must be selected against performance, integration and compliance requirements. | P26: ="Selection should confirm the model-specific operating range, capacity, accuracy, interfaces, utilities, accessories, standards, environmental limits and service requirements. Final capabilities depend on the approved "&E26&" configuration." -> Selection should confirm the model-specific operating range, capacity, accuracy, interfaces, utilities, accessories, standards, environmental limits and service requirements. Final capabilities depend on the approved ChroZen ASTM D5580 Player configuration. | R26: =B26&" applications; laboratory research, engineering development, quality control and industrial deployment where applicable. Suitability must be confirmed against the user's sample, process, environment and required standards." -> Analyzers applications; laboratory research, engineering development, quality control and industrial deployment where applicable. Suitability must be confirmed against the user's sample, process, environment and required standards. | T26: =E26&" from "&C26 -> ChroZen ASTM D5580 Player from Young In Chromass | V26: No public downloadable document captured yet; provide the latest approved manufacturer document on request after revision and reuse checks. | W26: ="See other "&B26&" products" -> See other Analyzers products | X26: =B26&" enquiry → website group enquiry form → category owner assignment" -> Analyzers enquiry → website group enquiry form → category owner assignment | Y26: =E26&", "&B26&", "&C26&", technical equipment, DIWAN" -> ChroZen ASTM D5580 Player, Analyzers, Young In Chromass, technical equipment, DIWAN | Z26: https://eng.youngincm.com/goods/list.php?M2_IDX=18659 | AA26: 46257 | AB26: Product Team / Technical Reviewer | AC26: =IF(AND(O26<>"",P26<>"",R26<>"",T26<>"",X26<>"",Y26<>"",Z26<>"",AA26<>"",AB26<>""),IF(AND(Q26<>"",S26<>"",U26<>""),"Ready for approval","Content drafted - assets/specs pending"),IF(COUNTA(O26:AB26)=0,"Not started","In progress")) -> Content drafted - assets/specs pending | AD26: ="Baseline definition created from the official catalog name, partner and category classification ("&G26&"). Model-specific specifications, images and downloadable documents must be extracted from the linked official source and technically approved before publication. Source register reviewed 2026-08-23." -> Baseline definition created from the official catalog name, partner and category classification (One page per product category). Model-specific specifications, images and downloadable documents must be extracted from the linked official source and technically approved before publication. Source register reviewed 2026-08-23. | AG26: Availability, configuration and commercial supply are subject to confirmation by DIWAN and the manufacturer. | AH26: Lead time is confirmed in the formal quotation; do not publish a fixed delivery commitment. | AI26: Publish manufacturer documents only when public access and reuse are permitted; otherwise provide controlled access on request.
A27: =IF(B27=B26,A26,A26+1) -> 5 | B27: Analyzers | C27: Young In Chromass | D27: South Korea | E27: ChroZen USP 467 Player (Residual Solvent Analyzer) | F27: /products/analyzers | G27: One page per product category | H27: 46257 | I27: ChroZen USP 467 Player (Residual Solvent Analyzer) | DIWAN Engineering & Technology Company | J27: chrozen-usp-467-player-residual-solvent-analyzer | K27: =E27&" is "&IF(ISNUMBER(SEARCH(LEFT(LOWER(B27),1),"aeiou")),"an ","a ")&LOWER(B27)&" product from "&C27&" for application-specific laboratory, engineering or industrial use." -> ChroZen USP 467 Player (Residual Solvent Analyzer) is an analyzers product from Young In Chromass for application-specific laboratory, engineering or industrial use. | L27: =E27&" from "&C27&" for "&LOWER(B27)&" applications. Review configuration requirements and request technical information or a quotation from DIWAN." -> ChroZen USP 467 Player (Residual Solvent Analyzer) from Young In Chromass for analyzers applications. Review configuration requirements and request technical information or a quotation from DIWAN. | M27: Request technical information or a quote | N27: Baseline definition complete - official specifications and assets pending | O27: {=_xlfn.LET(_xlpm.n,LOWER(E27),_xlpm.c,LOWER(B27),_xlpm.t,_xlfn.IFS(OR(ISNUMBER(SEARCH("lens",_xlpm.n)),ISNUMBER(SEARCH("optic",_xlpm.n)),ISNUMBER(SEARCH("polarizer",_xlpm.n))),"precision optical component",OR(ISNUMBER(SEARCH("camera",_xlpm.n)),ISNUMBER(SEARCH("imaging",_xlpm.n))),"scientific or industrial imaging system",ISNUMBER(SEARCH("pump",_xlpm.n)),"precision fluid-delivery system",OR(ISNUMBER(SEARCH("reactor",_xlpm.n)),ISNUMBER(SEARCH("autoclave",_xlpm.n)),ISNUMBER(SEARCH("pilot",_xlpm.n))),"laboratory or pilot-process system",OR(ISNUMBER(SEARCH("analyzer",_xlpm.n)),ISNUMBER(SEARCH("spectrometer",_xlpm.n)),ISNUMBER(SEARCH("hplc",_xlpm.n)),ISNUMBER(SEARCH("chrom",_xlpm.n))),"analytical laboratory instrument",OR(ISNUMBER(SEARCH("tester",_xlpm.n)),ISNUMBER(SEARCH("testing machine",_xlpm.n)),ISNUMBER(SEARCH("chamber",_xlpm.n))),"materials or component testing system",OR(ISNUMBER(SEARCH("sensor",_xlpm.n)),ISNUMBER(SEARCH("terminal",_xlpm.n)),ISNUMBER(SEARCH("station",_xlpm.n)),ISNUMBER(SEARCH("satellite",_xlpm.n))),"space or sensing subsystem",ISNUMBER(SEARCH("software",_xlpm.n)),"specialized engineering software platform",TRUE,"specialized "&_xlpm.c&" product"),_xlpm.art,IF(ISNUMBER(SEARCH(LEFT(_xlpm.t,1),"aeiou")),"an ","a "),E27&" is "&_xlpm.art&_xlpm.t&" from "&C27&" designed for application-specific laboratory, engineering or industrial use. It belongs to DIWAN's "&B27&" portfolio; final configuration must be selected against performance, integration and compliance requirements.")} -> ChroZen USP 467 Player (Residual Solvent Analyzer) is an analytical laboratory instrument from Young In Chromass designed for application-specific laboratory, engineering or industrial use. It belongs to DIWAN's Analyzers portfolio; final configuration must be selected against performance, integration and compliance requirements. | P27: ="Selection should confirm the model-specific operating range, capacity, accuracy, interfaces, utilities, accessories, standards, environmental limits and service requirements. Final capabilities depend on the approved "&E27&" configuration." -> Selection should confirm the model-specific operating range, capacity, accuracy, interfaces, utilities, accessories, standards, environmental limits and service requirements. Final capabilities depend on the approved ChroZen USP 467 Player (Residual Solvent Analyzer) configuration. | R27: =B27&" applications; laboratory research, engineering development, quality control and industrial deployment where applicable. Suitability must be confirmed against the user's sample, process, environment and required standards." -> Analyzers applications; laboratory research, engineering development, quality control and industrial deployment where applicable. Suitability must be confirmed against the user's sample, process, environment and required standards. | T27: =E27&" from "&C27 -> ChroZen USP 467 Player (Residual Solvent Analyzer) from Young In Chromass | V27: No public downloadable document captured yet; provide the latest approved manufacturer document on request after revision and reuse checks. | W27: ="See other "&B27&" products" -> See other Analyzers products | X27: =B27&" enquiry → website group enquiry form → category owner assignment" -> Analyzers enquiry → website group enquiry form → category owner assignment | Y27: =E27&", "&B27&", "&C27&", technical equipment, DIWAN" -> ChroZen USP 467 Player (Residual Solvent Analyzer), Analyzers, Young In Chromass, technical equipment, DIWAN | Z27: https://eng.youngincm.com/goods/list.php?M2_IDX=18659 | AA27: 46257 | AB27: Product Team / Technical Reviewer | AC27: =IF(AND(O27<>"",P27<>"",R27<>"",T27<>"",X27<>"",Y27<>"",Z27<>"",AA27<>"",AB27<>""),IF(AND(Q27<>"",S27<>"",U27<>""),"Ready for approval","Content drafted - assets/specs pending"),IF(COUNTA(O27:AB27)=0,"Not started","In progress")) -> Content drafted - assets/specs pending | AD27: ="Baseline definition created from the official catalog name, partner and category classification ("&G27&"). Model-specific specifications, images and downloadable documents must be extracted from the linked official source and technically approved before publication. Source register reviewed 2026-08-23." -> Baseline definition created from the official catalog name, partner and category classification (One page per product category). Model-specific specifications, images and downloadable documents must be extracted from the linked official source and technically approved before publication. Source register reviewed 2026-08-23. | AG27: Availability, configuration and commercial supply are subject to confirmation by DIWAN and the manufacturer. | AH27: Lead time is confirmed in the formal quotation; do not publish a fixed delivery commitment. | AI27: Publish manufacturer documents only when public access and reuse are permitted; otherwise provide controlled access on request.
A28: =IF(B28=B27,A27,A27+1) -> 5 | B28: Analyzers | C28: Young In Chromass | D28: South Korea | E28: ChroZen ASTM D1945 Player | F28: /products/analyzers | G28: One page per product category | H28: 46257 | I28: ChroZen ASTM D1945 Player | DIWAN Engineering & Technology Company | J28: chrozen-astm-d1945-player | K28: =E28&" is "&IF(ISNUMBER(SEARCH(LEFT(LOWER(B28),1),"aeiou")),"an ","a ")&LOWER(B28)&" product from "&C28&" for application-specific laboratory, engineering or industrial use." -> ChroZen ASTM D1945 Player is an analyzers product from Young In Chromass for application-specific laboratory, engineering or industrial use. | L28: =E28&" from "&C28&" for "&LOWER(B28)&" applications. Review configuration requirements and request technical information or a quotation from DIWAN." -> ChroZen ASTM D1945 Player from Young In Chromass for analyzers applications. Review configuration requirements and request technical information or a quotation from DIWAN. | M28: Request technical information or a quote | N28: Baseline definition complete - official specifications and assets pending | O28: {=_xlfn.LET(_xlpm.n,LOWER(E28),_xlpm.c,LOWER(B28),_xlpm.t,_xlfn.IFS(OR(ISNUMBER(SEARCH("lens",_xlpm.n)),ISNUMBER(SEARCH("optic",_xlpm.n)),ISNUMBER(SEARCH("polarizer",_xlpm.n))),"precision optical component",OR(ISNUMBER(SEARCH("camera",_xlpm.n)),ISNUMBER(SEARCH("imaging",_xlpm.n))),"scientific or industrial imaging system",ISNUMBER(SEARCH("pump",_xlpm.n)),"precision fluid-delivery system",OR(ISNUMBER(SEARCH("reactor",_xlpm.n)),ISNUMBER(SEARCH("autoclave",_xlpm.n)),ISNUMBER(SEARCH("pilot",_xlpm.n))),"laboratory or pilot-process system",OR(ISNUMBER(SEARCH("analyzer",_xlpm.n)),ISNUMBER(SEARCH("spectrometer",_xlpm.n)),ISNUMBER(SEARCH("hplc",_xlpm.n)),ISNUMBER(SEARCH("chrom",_xlpm.n))),"analytical laboratory instrument",OR(ISNUMBER(SEARCH("tester",_xlpm.n)),ISNUMBER(SEARCH("testing machine",_xlpm.n)),ISNUMBER(SEARCH("chamber",_xlpm.n))),"materials or component testing system",OR(ISNUMBER(SEARCH("sensor",_xlpm.n)),ISNUMBER(SEARCH("terminal",_xlpm.n)),ISNUMBER(SEARCH("station",_xlpm.n)),ISNUMBER(SEARCH("satellite",_xlpm.n))),"space or sensing subsystem",ISNUMBER(SEARCH("software",_xlpm.n)),"specialized engineering software platform",TRUE,"specialized "&_xlpm.c&" product"),_xlpm.art,IF(ISNUMBER(SEARCH(LEFT(_xlpm.t,1),"aeiou")),"an ","a "),E28&" is "&_xlpm.art&_xlpm.t&" from "&C28&" designed for application-specific laboratory, engineering or industrial use. It belongs to DIWAN's "&B28&" portfolio; final configuration must be selected against performance, integration and compliance requirements.")} -> ChroZen ASTM D1945 Player is a specialized analyzers product from Young In Chromass designed for application-specific laboratory, engineering or industrial use. It belongs to DIWAN's Analyzers portfolio; final configuration must be selected against performance, integration and compliance requirements. | P28: ="Selection should confirm the model-specific operating range, capacity, accuracy, interfaces, utilities, accessories, standards, environmental limits and service requirements. Final capabilities depend on the approved "&E28&" configuration." -> Selection should confirm the model-specific operating range, capacity, accuracy, interfaces, utilities, accessories, standards, environmental limits and service requirements. Final capabilities depend on the approved ChroZen ASTM D1945 Player configuration. | R28: =B28&" applications; laboratory research, engineering development, quality control and industrial deployment where applicable. Suitability must be confirmed against the user's sample, process, environment and required standards." -> Analyzers applications; laboratory research, engineering development, quality control and industrial deployment where applicable. Suitability must be confirmed against the user's sample, process, environment and required standards. | T28: =E28&" from "&C28 -> ChroZen ASTM D1945 Player from Young In Chromass | V28: No public downloadable document captured yet; provide the latest approved manufacturer document on request after revision and reuse checks. | W28: ="See other "&B28&" products" -> See other Analyzers products | X28: =B28&" enquiry → website group enquiry form → category owner assignment" -> Analyzers enquiry → website group enquiry form → category owner assignment | Y28: =E28&", "&B28&", "&C28&", technical equipment, DIWAN" -> ChroZen ASTM D1945 Player, Analyzers, Young In Chromass, technical equipment, DIWAN | Z28: https://eng.youngincm.com/goods/list.php?M2_IDX=18659 | AA28: 46257 | AB28: Product Team / Technical Reviewer | AC28: =IF(AND(O28<>"",P28<>"",R28<>"",T28<>"",X28<>"",Y28<>"",Z28<>"",AA28<>"",AB28<>""),IF(AND(Q28<>"",S28<>"",U28<>""),"Ready for approval","Content drafted - assets/specs pending"),IF(COUNTA(O28:AB28)=0,"Not started","In progress")) -> Content drafted - assets/specs pending | AD28: ="Baseline definition created from the official catalog name, partner and category classification ("&G28&"). Model-specific specifications, images and downloadable documents must be extracted from the linked official source and technically approved before publication. Source register reviewed 2026-08-23." -> Baseline definition created from the official catalog name, partner and category classification (One page per product category). Model-specific specifications, images and downloadable documents must be extracted from the linked official source and technically approved before publication. Source register reviewed 2026-08-23. | AG28: Availability, configuration and commercial supply are subject to confirmation by DIWAN and the manufacturer. | AH28: Lead time is confirmed in the formal quotation; do not publish a fixed delivery commitment. | AI28: Publish manufacturer documents only when public access and reuse are permitted; otherwise provide controlled access on request.
A29: =IF(B29=B28,A28,A28+1) -> 5 | B29: Analyzers | C29: Young In Chromass | D29: South Korea | E29: Biodiesel Analyzer | F29: /products/analyzers | G29: One page per product category | H29: 46257 | I29: Biodiesel Analyzer | DIWAN Engineering & Technology Company | J29: biodiesel-analyzer | K29: =E29&" is "&IF(ISNUMBER(SEARCH(LEFT(LOWER(B29),1),"aeiou")),"an ","a ")&LOWER(B29)&" product from "&C29&" for application-specific laboratory, engineering or industrial use." -> Biodiesel Analyzer is an analyzers product from Young In Chromass for application-specific laboratory, engineering or industrial use. | L29: =E29&" from "&C29&" for "&LOWER(B29)&" applications. Review configuration requirements and request technical information or a quotation from DIWAN." -> Biodiesel Analyzer from Young In Chromass for analyzers applications. Review configuration requirements and request technical information or a quotation from DIWAN. | M29: Request technical information or a quote | N29: Baseline definition complete - official specifications and assets pending | O29: {=_xlfn.LET(_xlpm.n,LOWER(E29),_xlpm.c,LOWER(B29),_xlpm.t,_xlfn.IFS(OR(ISNUMBER(SEARCH("lens",_xlpm.n)),ISNUMBER(SEARCH("optic",_xlpm.n)),ISNUMBER(SEARCH("polarizer",_xlpm.n))),"precision optical component",OR(ISNUMBER(SEARCH("camera",_xlpm.n)),ISNUMBER(SEARCH("imaging",_xlpm.n))),"scientific or industrial imaging system",ISNUMBER(SEARCH("pump",_xlpm.n)),"precision fluid-delivery system",OR(ISNUMBER(SEARCH("reactor",_xlpm.n)),ISNUMBER(SEARCH("autoclave",_xlpm.n)),ISNUMBER(SEARCH("pilot",_xlpm.n))),"laboratory or pilot-process system",OR(ISNUMBER(SEARCH("analyzer",_xlpm.n)),ISNUMBER(SEARCH("spectrometer",_xlpm.n)),ISNUMBER(SEARCH("hplc",_xlpm.n)),ISNUMBER(SEARCH("chrom",_xlpm.n))),"analytical laboratory instrument",OR(ISNUMBER(SEARCH("tester",_xlpm.n)),ISNUMBER(SEARCH("testing machine",_xlpm.n)),ISNUMBER(SEARCH("chamber",_xlpm.n))),"materials or component testing system",OR(ISNUMBER(SEARCH("sensor",_xlpm.n)),ISNUMBER(SEARCH("terminal",_xlpm.n)),ISNUMBER(SEARCH("station",_xlpm.n)),ISNUMBER(SEARCH("satellite",_xlpm.n))),"space or sensing subsystem",ISNUMBER(SEARCH("software",_xlpm.n)),"specialized engineering software platform",TRUE,"specialized "&_xlpm.c&" product"),_xlpm.art,IF(ISNUMBER(SEARCH(LEFT(_xlpm.t,1),"aeiou")),"an ","a "),E29&" is "&_xlpm.art&_xlpm.t&" from "&C29&" designed for application-specific laboratory, engineering or industrial use. It belongs to DIWAN's "&B29&" portfolio; final configuration must be selected against performance, integration and compliance requirements.")} -> Biodiesel Analyzer is an analytical laboratory instrument from Young In Chromass designed for application-specific laboratory, engineering or industrial use. It belongs to DIWAN's Analyzers portfolio; final configuration must be selected against performance, integration and compliance requirements. | P29: ="Selection should confirm the model-specific operating range, capacity, accuracy, interfaces, utilities, accessories, standards, environmental limits and service requirements. Final capabilities depend on the approved "&E29&" configuration." -> Selection should confirm the model-specific operating range, capacity, accuracy, interfaces, utilities, accessories, standards, environmental limits and service requirements. Final capabilities depend on the approved Biodiesel Analyzer configuration. | R29: =B29&" applications; laboratory research, engineering development, quality control and industrial deployment where applicable. Suitability must be confirmed against the user's sample, process, environment and required standards." -> Analyzers applications; laboratory research, engineering development, quality control and industrial deployment where applicable. Suitability must be confirmed against the user's sample, process, environment and required standards. | T29: =E29&" from "&C29 -> Biodiesel Analyzer from Young In Chromass | V29: No public downloadable document captured yet; provide the latest approved manufacturer document on request after revision and reuse checks. | W29: ="See other "&B29&" products" -> See other Analyzers products | X29: =B29&" enquiry → website group enquiry form → category owner assignment" -> Analyzers enquiry → website group enquiry form → category owner assignment | Y29: =E29&", "&B29&", "&C29&", technical equipment, DIWAN" -> Biodiesel Analyzer, Analyzers, Young In Chromass, technical equipment, DIWAN | Z29: https://eng.youngincm.com/goods/list.php?M2_IDX=18659 | AA29: 46257 | AB29: Product Team / Technical Reviewer | AC29: =IF(AND(O29<>"",P29<>"",R29<>"",T29<>"",X29<>"",Y29<>"",Z29<>"",AA29<>"",AB29<>""),IF(AND(Q29<>"",S29<>"",U29<>""),"Ready for approval","Content drafted - assets/specs pending"),IF(COUNTA(O29:AB29)=0,"Not started","In progress")) -> Content drafted - assets/specs pending | AD29: ="Baseline definition created from the official catalog name, partner and category classification ("&G29&"). Model-specific specifications, images and downloadable documents must be extracted from the linked official source and technically approved before publication. Source register reviewed 2026-08-23." -> Baseline definition created from the official catalog name, partner and category classification (One page per product category). Model-specific specifications, images and downloadable documents must be extracted from the linked official source and technically approved before publication. Source register reviewed 2026-08-23. | AG29: Availability, configuration and commercial supply are subject to confirmation by DIWAN and the manufacturer. | AH29: Lead time is confirmed in the formal quotation; do not publish a fixed delivery commitment. | AI29: Publish manufacturer documents only when public access and reuse are permitted; otherwise provide controlled access on request.
A30: =IF(B30=B29,A29,A29+1) -> 5 | B30: Analyzers | C30: Young In Chromass | D30: South Korea | E30: Phthalate Analyzer | F30: /products/analyzers | G30: One page per product category | H30: 46257 | I30: Phthalate Analyzer | DIWAN Engineering & Technology Company | J30: phthalate-analyzer | K30: =E30&" is "&IF(ISNUMBER(SEARCH(LEFT(LOWER(B30),1),"aeiou")),"an ","a ")&LOWER(B30)&" product from "&C30&" for application-specific laboratory, engineering or industrial use." -> Phthalate Analyzer is an analyzers product from Young In Chromass for application-specific laboratory, engineering or industrial use. | L30: =E30&" from "&C30&" for "&LOWER(B30)&" applications. Review configuration requirements and request technical information or a quotation from DIWAN." -> Phthalate Analyzer from Young In Chromass for analyzers applications. Review configuration requirements and request technical information or a quotation from DIWAN. | M30: Request technical information or a quote | N30: Baseline definition complete - official specifications and assets pending | O30: {=_xlfn.LET(_xlpm.n,LOWER(E30),_xlpm.c,LOWER(B30),_xlpm.t,_xlfn.IFS(OR(ISNUMBER(SEARCH("lens",_xlpm.n)),ISNUMBER(SEARCH("optic",_xlpm.n)),ISNUMBER(SEARCH("polarizer",_xlpm.n))),"precision optical component",OR(ISNUMBER(SEARCH("camera",_xlpm.n)),ISNUMBER(SEARCH("imaging",_xlpm.n))),"scientific or industrial imaging system",ISNUMBER(SEARCH("pump",_xlpm.n)),"precision fluid-delivery system",OR(ISNUMBER(SEARCH("reactor",_xlpm.n)),ISNUMBER(SEARCH("autoclave",_xlpm.n)),ISNUMBER(SEARCH("pilot",_xlpm.n))),"laboratory or pilot-process system",OR(ISNUMBER(SEARCH("analyzer",_xlpm.n)),ISNUMBER(SEARCH("spectrometer",_xlpm.n)),ISNUMBER(SEARCH("hplc",_xlpm.n)),ISNUMBER(SEARCH("chrom",_xlpm.n))),"analytical laboratory instrument",OR(ISNUMBER(SEARCH("tester",_xlpm.n)),ISNUMBER(SEARCH("testing machine",_xlpm.n)),ISNUMBER(SEARCH("chamber",_xlpm.n))),"materials or component testing system",OR(ISNUMBER(SEARCH("sensor",_xlpm.n)),ISNUMBER(SEARCH("terminal",_xlpm.n)),ISNUMBER(SEARCH("station",_xlpm.n)),ISNUMBER(SEARCH("satellite",_xlpm.n))),"space or sensing subsystem",ISNUMBER(SEARCH("software",_xlpm.n)),"specialized engineering software platform",TRUE,"specialized "&_xlpm.c&" product"),_xlpm.art,IF(ISNUMBER(SEARCH(LEFT(_xlpm.t,1),"aeiou")),"an ","a "),E30&" is "&_xlpm.art&_xlpm.t&" from "&C30&" designed for application-specific laboratory, engineering or industrial use. It belongs to DIWAN's "&B30&" portfolio; final configuration must be selected against performance, integration and compliance requirements.")} -> Phthalate Analyzer is an analytical laboratory instrument from Young In Chromass designed for application-specific laboratory, engineering or industrial use. It belongs to DIWAN's Analyzers portfolio; final configuration must be selected against performance, integration and compliance requirements. | P30: ="Selection should confirm the model-specific operating range, capacity, accuracy, interfaces, utilities, accessories, standards, environmental limits and service requirements. Final capabilities depend on the approved "&E30&" configuration." -> Selection should confirm the model-specific operating range, capacity, accuracy, interfaces, utilities, accessories, standards, environmental limits and service requirements. Final capabilities depend on the approved Phthalate Analyzer configuration. | R30: =B30&" applications; laboratory research, engineering development, quality control and industrial deployment where applicable. Suitability must be confirmed against the user's sample, process, environment and required standards." -> Analyzers applications; laboratory research, engineering development, quality control and industrial deployment where applicable. Suitability must be confirmed against the user's sample, process, environment and required standards. | T30: =E30&" from "&C30 -> Phthalate Analyzer from Young In Chromass | V30: No public downloadable document captured yet; provide the latest approved manufacturer document on request after revision and reuse checks. | W30: ="See other "&B30&" products" -> See other Analyzers products | X30: =B30&" enquiry → website group enquiry form → category owner assignment" -> Analyzers enquiry → website group enquiry form → category owner assignment | Y30: =E30&", "&B30&", "&C30&", technical equipment, DIWAN" -> Phthalate Analyzer, Analyzers, Young In Chromass, technical equipment, DIWAN | Z30: https://eng.youngincm.com/goods/list.php?M2_IDX=18659 | AA30: 46257 | AB30: Product Team / Technical Reviewer | AC30: =IF(AND(O30<>"",P30<>"",R30<>"",T30<>"",X30<>"",Y30<>"",Z30<>"",AA30<>"",AB30<>""),IF(AND(Q30<>"",S30<>"",U30<>""),"Ready for approval","Content drafted - assets/specs pending"),IF(COUNTA(O30:AB30)=0,"Not started","In progress")) -> Content drafted - assets/specs pending | AD30: ="Baseline definition created from the official catalog name, partner and category classification ("&G30&"). Model-specific specifications, images and downloadable documents must be extracted from the linked official source and technically approved before publication. Source register reviewed 2026-08-23." -> Baseline definition created from the official catalog name, partner and category classification (One page per product category). Model-specific specifications, images and downloadable documents must be extracted from the linked official source and technically approved before publication. Source register reviewed 2026-08-23. | AG30: Availability, configuration and commercial supply are subject to confirmation by DIWAN and the manufacturer. | AH30: Lead time is confirmed in the formal quotation; do not publish a fixed delivery commitment. | AI30: Publish manufacturer documents only when public access and reuse are permitted; otherwise provide controlled access on request.
A31: =IF(B31=B30,A30,A30+1) -> 5 | B31: Analyzers | C31: Young In Chromass | D31: South Korea | E31: Fatty Acid Analyzer | F31: /products/analyzers | G31: One page per product category | H31: 46257 | I31: Fatty Acid Analyzer | DIWAN Engineering & Technology Company | J31: fatty-acid-analyzer | K31: =E31&" is "&IF(ISNUMBER(SEARCH(LEFT(LOWER(B31),1),"aeiou")),"an ","a ")&LOWER(B31)&" product from "&C31&" for application-specific laboratory, engineering or industrial use." -> Fatty Acid Analyzer is an analyzers product from Young In Chromass for application-specific laboratory, engineering or industrial use. | L31: =E31&" from "&C31&" for "&LOWER(B31)&" applications. Review configuration requirements and request technical information or a quotation from DIWAN." -> Fatty Acid Analyzer from Young In Chromass for analyzers applications. Review configuration requirements and request technical information or a quotation from DIWAN. | M31: Request technical information or a quote | N31: Baseline definition complete - official specifications and assets pending | O31: {=_xlfn.LET(_xlpm.n,LOWER(E31),_xlpm.c,LOWER(B31),_xlpm.t,_xlfn.IFS(OR(ISNUMBER(SEARCH("lens",_xlpm.n)),ISNUMBER(SEARCH("optic",_xlpm.n)),ISNUMBER(SEARCH("polarizer",_xlpm.n))),"precision optical component",OR(ISNUMBER(SEARCH("camera",_xlpm.n)),ISNUMBER(SEARCH("imaging",_xlpm.n))),"scientific or industrial imaging system",ISNUMBER(SEARCH("pump",_xlpm.n)),"precision fluid-delivery system",OR(ISNUMBER(SEARCH("reactor",_xlpm.n)),ISNUMBER(SEARCH("autoclave",_xlpm.n)),ISNUMBER(SEARCH("pilot",_xlpm.n))),"laboratory or pilot-process system",OR(ISNUMBER(SEARCH("analyzer",_xlpm.n)),ISNUMBER(SEARCH("spectrometer",_xlpm.n)),ISNUMBER(SEARCH("hplc",_xlpm.n)),ISNUMBER(SEARCH("chrom",_xlpm.n))),"analytical laboratory instrument",OR(ISNUMBER(SEARCH("tester",_xlpm.n)),ISNUMBER(SEARCH("testing machine",_xlpm.n)),ISNUMBER(SEARCH("chamber",_xlpm.n))),"materials or component testing system",OR(ISNUMBER(SEARCH("sensor",_xlpm.n)),ISNUMBER(SEARCH("terminal",_xlpm.n)),ISNUMBER(SEARCH("station",_xlpm.n)),ISNUMBER(SEARCH("satellite",_xlpm.n))),"space or sensing subsystem",ISNUMBER(SEARCH("software",_xlpm.n)),"specialized engineering software platform",TRUE,"specialized "&_xlpm.c&" product"),_xlpm.art,IF(ISNUMBER(SEARCH(LEFT(_xlpm.t,1),"aeiou")),"an ","a "),E31&" is "&_xlpm.art&_xlpm.t&" from "&C31&" designed for application-specific laboratory, engineering or industrial use. It belongs to DIWAN's "&B31&" portfolio; final configuration must be selected against performance, integration and compliance requirements.")} -> Fatty Acid Analyzer is an analytical laboratory instrument from Young In Chromass designed for application-specific laboratory, engineering or industrial use. It belongs to DIWAN's Analyzers portfolio; final configuration must be selected against performance, integration and compliance requirements. | P31: ="Selection should confirm the model-specific operating range, capacity, accuracy, interfaces, utilities, accessories, standards, environmental limits and service requirements. Final capabilities depend on the approved "&E31&" configuration." -> Selection should confirm the model-specific operating range, capacity, accuracy, interfaces, utilities, accessories, standards, environmental limits and service requirements. Final capabilities depend on the approved Fatty Acid Analyzer configuration. | R31: =B31&" applications; laboratory research, engineering development, quality control and industrial deployment where applicable. Suitability must be confirmed against the user's sample, process, environment and required standards." -> Analyzers applications; laboratory research, engineering development, quality control and industrial deployment where applicable. Suitability must be confirmed against the user's sample, process, environment and required standards. | T31: =E31&" from "&C31 -> Fatty Acid Analyzer from Young In Chromass | V31: No public downloadable document captured yet; provide the latest approved manufacturer document on request after revision and reuse checks. | W31: ="See other "&B31&" products" -> See other Analyzers products | X31: =B31&" enquiry → website group enquiry form → category owner assignment" -> Analyzers enquiry → website group enquiry form → category owner assignment | Y31: =E31&", "&B31&", "&C31&", technical equipment, DIWAN" -> Fatty Acid Analyzer, Analyzers, Young In Chromass, technical equipment, DIWAN | Z31: https://eng.youngincm.com/goods/list.php?M2_IDX=18659 | AA31: 46257 | AB31: Product Team / Technical Reviewer | AC31: =IF(AND(O31<>"",P31<>"",R31<>"",T31<>"",X31<>"",Y31<>"",Z31<>"",AA31<>"",AB31<>""),IF(AND(Q31<>"",S31<>"",U31<>""),"Ready for approval","Content drafted - assets/specs pending"),IF(COUNTA(O31:AB31)=0,"Not started","In progress")) -> Content drafted - assets/specs pending | AD31: ="Baseline definition created from the official catalog name, partner and category classification ("&G31&"). Model-specific specifications, images and downloadable documents must be extracted from the linked official source and technically approved before publication. Source register reviewed 2026-08-23." -> Baseline definition created from the official catalog name, partner and category classification (One page per product category). Model-specific specifications, images and downloadable documents must be extracted from the linked official source and technically approved before publication. Source register reviewed 2026-08-23. | AG31: Availability, configuration and commercial supply are subject to confirmation by DIWAN and the manufacturer. | AH31: Lead time is confirmed in the formal quotation; do not publish a fixed delivery commitment. | AI31: Publish manufacturer documents only when public access and reuse are permitted; otherwise provide controlled access on request.
A32: =IF(B32=B31,A31,A31+1) -> 5 | B32: Analyzers | C32: Young In Chromass | D32: South Korea | E32: VOC Analyzer | F32: /products/analyzers | G32: One page per product category | H32: 46257 | I32: VOC Analyzer | DIWAN Engineering & Technology Company | J32: voc-analyzer | K32: =E32&" is "&IF(ISNUMBER(SEARCH(LEFT(LOWER(B32),1),"aeiou")),"an ","a ")&LOWER(B32)&" product from "&C32&" for application-specific laboratory, engineering or industrial use." -> VOC Analyzer is an analyzers product from Young In Chromass for application-specific laboratory, engineering or industrial use. | L32: =E32&" from "&C32&" for "&LOWER(B32)&" applications. Review configuration requirements and request technical information or a quotation from DIWAN." -> VOC Analyzer from Young In Chromass for analyzers applications. Review configuration requirements and request technical information or a quotation from DIWAN. | M32: Request technical information or a quote | N32: Baseline definition complete - official specifications and assets pending | O32: {=_xlfn.LET(_xlpm.n,LOWER(E32),_xlpm.c,LOWER(B32),_xlpm.t,_xlfn.IFS(OR(ISNUMBER(SEARCH("lens",_xlpm.n)),ISNUMBER(SEARCH("optic",_xlpm.n)),ISNUMBER(SEARCH("polarizer",_xlpm.n))),"precision optical component",OR(ISNUMBER(SEARCH("camera",_xlpm.n)),ISNUMBER(SEARCH("imaging",_xlpm.n))),"scientific or industrial imaging system",ISNUMBER(SEARCH("pump",_xlpm.n)),"precision fluid-delivery system",OR(ISNUMBER(SEARCH("reactor",_xlpm.n)),ISNUMBER(SEARCH("autoclave",_xlpm.n)),ISNUMBER(SEARCH("pilot",_xlpm.n))),"laboratory or pilot-process system",OR(ISNUMBER(SEARCH("analyzer",_xlpm.n)),ISNUMBER(SEARCH("spectrometer",_xlpm.n)),ISNUMBER(SEARCH("hplc",_xlpm.n)),ISNUMBER(SEARCH("chrom",_xlpm.n))),"analytical laboratory instrument",OR(ISNUMBER(SEARCH("tester",_xlpm.n)),ISNUMBER(SEARCH("testing machine",_xlpm.n)),ISNUMBER(SEARCH("chamber",_xlpm.n))),"materials or component testing system",OR(ISNUMBER(SEARCH("sensor",_xlpm.n)),ISNUMBER(SEARCH("terminal",_xlpm.n)),ISNUMBER(SEARCH("station",_xlpm.n)),ISNUMBER(SEARCH("satellite",_xlpm.n))),"space or sensing subsystem",ISNUMBER(SEARCH("software",_xlpm.n)),"specialized engineering software platform",TRUE,"specialized "&_xlpm.c&" product"),_xlpm.art,IF(ISNUMBER(SEARCH(LEFT(_xlpm.t,1),"aeiou")),"an ","a "),E32&" is "&_xlpm.art&_xlpm.t&" from "&C32&" designed for application-specific laboratory, engineering or industrial use. It belongs to DIWAN's "&B32&" portfolio; final configuration must be selected against performance, integration and compliance requirements.")} -> VOC Analyzer is an analytical laboratory instrument from Young In Chromass designed for application-specific laboratory, engineering or industrial use. It belongs to DIWAN's Analyzers portfolio; final configuration must be selected against performance, integration and compliance requirements. | P32: ="Selection should confirm the model-specific operating range, capacity, accuracy, interfaces, utilities, accessories, standards, environmental limits and service requirements. Final capabilities depend on the approved "&E32&" configuration." -> Selection should confirm the model-specific operating range, capacity, accuracy, interfaces, utilities, accessories, standards, environmental limits and service requirements. Final capabilities depend on the approved VOC Analyzer configuration. | R32: =B32&" applications; laboratory research, engineering development, quality control and industrial deployment where applicable. Suitability must be confirmed against the user's sample, process, environment and required standards." -> Analyzers applications; laboratory research, engineering development, quality control and industrial deployment where applicable. Suitability must be confirmed against the user's sample, process, environment and required standards. | T32: =E32&" from "&C32 -> VOC Analyzer from Young In Chromass | V32: No public downloadable document captured yet; provide the latest approved manufacturer document on request after revision and reuse checks. | W32: ="See other "&B32&" products" -> See other Analyzers products | X32: =B32&" enquiry → website group enquiry form → category owner assignment" -> Analyzers enquiry → website group enquiry form → category owner assignment | Y32: =E32&", "&B32&", "&C32&", technical equipment, DIWAN" -> VOC Analyzer, Analyzers, Young In Chromass, technical equipment, DIWAN | Z32: https://eng.youngincm.com/goods/list.php?M2_IDX=18659 | AA32: 46257 | AB32: Product Team / Technical Reviewer | AC32: =IF(AND(O32<>"",P32<>"",R32<>"",T32<>"",X32<>"",Y32<>"",Z32<>"",AA32<>"",AB32<>""),IF(AND(Q32<>"",S32<>"",U32<>""),"Ready for approval","Content drafted - assets/specs pending"),IF(COUNTA(O32:AB32)=0,"Not started","In progress")) -> Content drafted - assets/specs pending | AD32: ="Baseline definition created from the official catalog name, partner and category classification ("&G32&"). Model-specific specifications, images and downloadable documents must be extracted from the linked official source and technically approved before publication. Source register reviewed 2026-08-23." -> Baseline definition created from the official catalog name, partner and category classification (One page per product category). Model-specific specifications, images and downloadable documents must be extracted from the linked official source and technically approved before publication. Source register reviewed 2026-08-23. | AG32: Availability, configuration and commercial supply are subject to confirmation by DIWAN and the manufacturer. | AH32: Lead time is confirmed in the formal quotation; do not publish a fixed delivery commitment. | AI32: Publish manufacturer documents only when public access and reuse are permitted; otherwise provide controlled access on request.
A33: =IF(B33=B32,A32,A32+1) -> 5 | B33: Analyzers | C33: Young In Chromass | D33: South Korea | E33: Sulfur Analyzer | F33: /products/analyzers | G33: One page per product category | H33: 46257 | I33: Sulfur Analyzer | DIWAN Engineering & Technology Company | J33: sulfur-analyzer | K33: =E33&" is "&IF(ISNUMBER(SEARCH(LEFT(LOWER(B33),1),"aeiou")),"an ","a ")&LOWER(B33)&" product from "&C33&" for application-specific laboratory, engineering or industrial use." -> Sulfur Analyzer is an analyzers product from Young In Chromass for application-specific laboratory, engineering or industrial use. | L33: =E33&" from "&C33&" for "&LOWER(B33)&" applications. Review configuration requirements and request technical information or a quotation from DIWAN." -> Sulfur Analyzer from Young In Chromass for analyzers applications. Review configuration requirements and request technical information or a quotation from DIWAN. | M33: Request technical information or a quote | N33: Baseline definition complete - official specifications and assets pending | O33: {=_xlfn.LET(_xlpm.n,LOWER(E33),_xlpm.c,LOWER(B33),_xlpm.t,_xlfn.IFS(OR(ISNUMBER(SEARCH("lens",_xlpm.n)),ISNUMBER(SEARCH("optic",_xlpm.n)),ISNUMBER(SEARCH("polarizer",_xlpm.n))),"precision optical component",OR(ISNUMBER(SEARCH("camera",_xlpm.n)),ISNUMBER(SEARCH("imaging",_xlpm.n))),"scientific or industrial imaging system",ISNUMBER(SEARCH("pump",_xlpm.n)),"precision fluid-delivery system",OR(ISNUMBER(SEARCH("reactor",_xlpm.n)),ISNUMBER(SEARCH("autoclave",_xlpm.n)),ISNUMBER(SEARCH("pilot",_xlpm.n))),"laboratory or pilot-process system",OR(ISNUMBER(SEARCH("analyzer",_xlpm.n)),ISNUMBER(SEARCH("spectrometer",_xlpm.n)),ISNUMBER(SEARCH("hplc",_xlpm.n)),ISNUMBER(SEARCH("chrom",_xlpm.n))),"analytical laboratory instrument",OR(ISNUMBER(SEARCH("tester",_xlpm.n)),ISNUMBER(SEARCH("testing machine",_xlpm.n)),ISNUMBER(SEARCH("chamber",_xlpm.n))),"materials or component testing system",OR(ISNUMBER(SEARCH("sensor",_xlpm.n)),ISNUMBER(SEARCH("terminal",_xlpm.n)),ISNUMBER(SEARCH("station",_xlpm.n)),ISNUMBER(SEARCH("satellite",_xlpm.n))),"space or sensing subsystem",ISNUMBER(SEARCH("software",_xlpm.n)),"specialized engineering software platform",TRUE,"specialized "&_xlpm.c&" product"),_xlpm.art,IF(ISNUMBER(SEARCH(LEFT(_xlpm.t,1),"aeiou")),"an ","a "),E33&" is "&_xlpm.art&_xlpm.t&" from "&C33&" designed for application-specific laboratory, engineering or industrial use. It belongs to DIWAN's "&B33&" portfolio; final configuration must be selected against performance, integration and compliance requirements.")} -> Sulfur Analyzer is an analytical laboratory instrument from Young In Chromass designed for application-specific laboratory, engineering or industrial use. It belongs to DIWAN's Analyzers portfolio; final configuration must be selected against performance, integration and compliance requirements. | P33: ="Selection should confirm the model-specific operating range, capacity, accuracy, interfaces, utilities, accessories, standards, environmental limits and service requirements. Final capabilities depend on the approved "&E33&" configuration." -> Selection should confirm the model-specific operating range, capacity, accuracy, interfaces, utilities, accessories, standards, environmental limits and service requirements. Final capabilities depend on the approved Sulfur Analyzer configuration. | R33: =B33&" applications; laboratory research, engineering development, quality control and industrial deployment where applicable. Suitability must be confirmed against the user's sample, process, environment and required standards." -> Analyzers applications; laboratory research, engineering development, quality control and industrial deployment where applicable. Suitability must be confirmed against the user's sample, process, environment and required standards. | T33: =E33&" from "&C33 -> Sulfur Analyzer from Young In Chromass | V33: No public downloadable document captured yet; provide the latest approved manufacturer document on request after revision and reuse checks. | W33: ="See other "&B33&" products" -> See other Analyzers products | X33: =B33&" enquiry → website group enquiry form → category owner assignment" -> Analyzers enquiry → website group enquiry form → category owner assignment | Y33: =E33&", "&B33&", "&C33&", technical equipment, DIWAN" -> Sulfur Analyzer, Analyzers, Young In Chromass, technical equipment, DIWAN | Z33: https://eng.youngincm.com/goods/list.php?M2_IDX=18659 | AA33: 46257 | AB33: Product Team / Technical Reviewer | AC33: =IF(AND(O33<>"",P33<>"",R33<>"",T33<>"",X33<>"",Y33<>"",Z33<>"",AA33<>"",AB33<>""),IF(AND(Q33<>"",S33<>"",U33<>""),"Ready for approval","Content drafted - assets/specs pending"),IF(COUNTA(O33:AB33)=0,"Not started","In progress")) -> Content drafted - assets/specs pending | AD33: ="Baseline definition created from the official catalog name, partner and category classification ("&G33&"). Model-specific specifications, images and downloadable documents must be extracted from the linked official source and technically approved before publication. Source register reviewed 2026-08-23." -> Baseline definition created from the official catalog name, partner and category classification (One page per product category). Model-specific specifications, images and downloadable documents must be extracted from the linked official source and technically approved before publication. Source register reviewed 2026-08-23. | AG33: Availability, configuration and commercial supply are subject to confirmation by DIWAN and the manufacturer. | AH33: Lead time is confirmed in the formal quotation; do not publish a fixed delivery commitment. | AI33: Publish manufacturer documents only when public access and reuse are permitted; otherwise provide controlled access on request.
A34: =IF(B34=B33,A33,A33+1) -> 5 | B34: Analyzers | C34: Young In Chromass | D34: South Korea | E34: Residual Solvent Analyzer | F34: /products/analyzers | G34: One page per product category | H34: 46257 | I34: Residual Solvent Analyzer | DIWAN Engineering & Technology Company | J34: residual-solvent-analyzer | K34: =E34&" is "&IF(ISNUMBER(SEARCH(LEFT(LOWER(B34),1),"aeiou")),"an ","a ")&LOWER(B34)&" product from "&C34&" for application-specific laboratory, engineering or industrial use." -> Residual Solvent Analyzer is an analyzers product from Young In Chromass for application-specific laboratory, engineering or industrial use. | L34: =E34&" from "&C34&" for "&LOWER(B34)&" applications. Review configuration requirements and request technical information or a quotation from DIWAN." -> Residual Solvent Analyzer from Young In Chromass for analyzers applications. Review configuration requirements and request technical information or a quotation from DIWAN. | M34: Request technical information or a quote | N34: Baseline definition complete - official specifications and assets pending | O34: {=_xlfn.LET(_xlpm.n,LOWER(E34),_xlpm.c,LOWER(B34),_xlpm.t,_xlfn.IFS(OR(ISNUMBER(SEARCH("lens",_xlpm.n)),ISNUMBER(SEARCH("optic",_xlpm.n)),ISNUMBER(SEARCH("polarizer",_xlpm.n))),"precision optical component",OR(ISNUMBER(SEARCH("camera",_xlpm.n)),ISNUMBER(SEARCH("imaging",_xlpm.n))),"scientific or industrial imaging system",ISNUMBER(SEARCH("pump",_xlpm.n)),"precision fluid-delivery system",OR(ISNUMBER(SEARCH("reactor",_xlpm.n)),ISNUMBER(SEARCH("autoclave",_xlpm.n)),ISNUMBER(SEARCH("pilot",_xlpm.n))),"laboratory or pilot-process system",OR(ISNUMBER(SEARCH("analyzer",_xlpm.n)),ISNUMBER(SEARCH("spectrometer",_xlpm.n)),ISNUMBER(SEARCH("hplc",_xlpm.n)),ISNUMBER(SEARCH("chrom",_xlpm.n))),"analytical laboratory instrument",OR(ISNUMBER(SEARCH("tester",_xlpm.n)),ISNUMBER(SEARCH("testing machine",_xlpm.n)),ISNUMBER(SEARCH("chamber",_xlpm.n))),"materials or component testing system",OR(ISNUMBER(SEARCH("sensor",_xlpm.n)),ISNUMBER(SEARCH("terminal",_xlpm.n)),ISNUMBER(SEARCH("station",_xlpm.n)),ISNUMBER(SEARCH("satellite",_xlpm.n))),"space or sensing subsystem",ISNUMBER(SEARCH("software",_xlpm.n)),"specialized engineering software platform",TRUE,"specialized "&_xlpm.c&" product"),_xlpm.art,IF(ISNUMBER(SEARCH(LEFT(_xlpm.t,1),"aeiou")),"an ","a "),E34&" is "&_xlpm.art&_xlpm.t&" from "&C34&" designed for application-specific laboratory, engineering or industrial use. It belongs to DIWAN's "&B34&" portfolio; final configuration must be selected against performance, integration and compliance requirements.")} -> Residual Solvent Analyzer is an analytical laboratory instrument from Young In Chromass designed for application-specific laboratory, engineering or industrial use. It belongs to DIWAN's Analyzers portfolio; final configuration must be selected against performance, integration and compliance requirements. | P34: ="Selection should confirm the model-specific operating range, capacity, accuracy, interfaces, utilities, accessories, standards, environmental limits and service requirements. Final capabilities depend on the approved "&E34&" configuration." -> Selection should confirm the model-specific operating range, capacity, accuracy, interfaces, utilities, accessories, standards, environmental limits and service requirements. Final capabilities depend on the approved Residual Solvent Analyzer configuration. | R34: =B34&" applications; laboratory research, engineering development, quality control and industrial deployment where applicable. Suitability must be confirmed against the user's sample, process, environment and required standards." -> Analyzers applications; laboratory research, engineering development, quality control and industrial deployment where applicable. Suitability must be confirmed against the user's sample, process, environment and required standards. | T34: =E34&" from "&C34 -> Residual Solvent Analyzer from Young In Chromass | V34: No public downloadable document captured yet; provide the latest approved manufacturer document on request after revision and reuse checks. | W34: ="See other "&B34&" products" -> See other Analyzers products | X34: =B34&" enquiry → website group enquiry form → category owner assignment" -> Analyzers enquiry → website group enquiry form → category owner assignment | Y34: =E34&", "&B34&", "&C34&", technical equipment, DIWAN" -> Residual Solvent Analyzer, Analyzers, Young In Chromass, technical equipment, DIWAN | Z34: https://eng.youngincm.com/goods/list.php?M2_IDX=18659 | AA34: 46257 | AB34: Product Team / Technical Reviewer | AC34: =IF(AND(O34<>"",P34<>"",R34<>"",T34<>"",X34<>"",Y34<>"",Z34<>"",AA34<>"",AB34<>""),IF(AND(Q34<>"",S34<>"",U34<>""),"Ready for approval","Content drafted - assets/specs pending"),IF(COUNTA(O34:AB34)=0,"Not started","In progress")) -> Content drafted - assets/specs pending | AD34: ="Baseline definition created from the official catalog name, partner and category classification ("&G34&"). Model-specific specifications, images and downloadable documents must be extracted from the linked official source and technically approved before publication. Source register reviewed 2026-08-23." -> Baseline definition created from the official catalog name, partner and category classification (One page per product category). Model-specific specifications, images and downloadable documents must be extracted from the linked official source and technically approved before publication. Source register reviewed 2026-08-23. | AG34: Availability, configuration and commercial supply are subject to confirmation by DIWAN and the manufacturer. | AH34: Lead time is confirmed in the formal quotation; do not publish a fixed delivery commitment. | AI34: Publish manufacturer documents only when public access and reuse are permitted; otherwise provide controlled access on request.
... A59: =IF(B59=B58,A58,A58+1) -> 10 | B59: Gas Chromatography | C59: Young In Chromass | D59: South Korea | E59: ChroZen GC-VUV | F59: /products/gas-chromatography | G59: One page per product category | H59: 46257 | I59: ChroZen GC-VUV | DIWAN Engineering & Technology Company | J59: chrozen-gc-vuv | K59: =E59&" is "&IF(ISNUMBER(SEARCH(LEFT(LOWER(B59),1),"aeiou")),"an ","a ")&LOWER(B59)&" product from "&C59&" for application-specific laboratory, engineering or industrial use." -> ChroZen GC-VUV is a gas chromatography product from Young In Chromass for application-specific laboratory, engineering or industrial use. | L59: =E59&" from "&C59&" for "&LOWER(B59)&" applications. Review configuration requirements and request technical information or a quotation from DIWAN." -> ChroZen GC-VUV from Young In Chromass for gas chromatography applications. Review configuration requirements and request technical information or a quotation from DIWAN. | M59: Request technical information or a quote | N59: Baseline definition complete - official specifications and assets pending | O59: {=_xlfn.LET(_xlpm.n,LOWER(E59),_xlpm.c,LOWER(B59),_xlpm.t,_xlfn.IFS(OR(ISNUMBER(SEARCH("lens",_xlpm.n)),ISNUMBER(SEARCH("optic",_xlpm.n)),ISNUMBER(SEARCH("polarizer",_xlpm.n))),"precision optical component",OR(ISNUMBER(SEARCH("camera",_xlpm.n)),ISNUMBER(SEARCH("imaging",_xlpm.n))),"scientific or industrial imaging system",ISNUMBER(SEARCH("pump",_xlpm.n)),"precision fluid-delivery system",OR(ISNUMBER(SEARCH("reactor",_xlpm.n)),ISNUMBER(SEARCH("autoclave",_xlpm.n)),ISNUMBER(SEARCH("pilot",_xlpm.n))),"laboratory or pilot-process system",OR(ISNUMBER(SEARCH("analyzer",_xlpm.n)),ISNUMBER(SEARCH("spectrometer",_xlpm.n)),ISNUMBER(SEARCH("hplc",_xlpm.n)),ISNUMBER(SEARCH("chrom",_xlpm.n))),"analytical laboratory instrument",OR(ISNUMBER(SEARCH("tester",_xlpm.n)),ISNUMBER(SEARCH("testing machine",_xlpm.n)),ISNUMBER(SEARCH("chamber",_xlpm.n))),"materials or component testing system",OR(ISNUMBER(SEARCH("sensor",_xlpm.n)),ISNUMBER(SEARCH("terminal",_xlpm.n)),ISNUMBER(SEARCH("station",_xlpm.n)),ISNUMBER(SEARCH("satellite",_xlpm.n))),"space or sensing subsystem",ISNUMBER(SEARCH("software",_xlpm.n)),"specialized engineering software platform",TRUE,"specialized "&_xlpm.c&" product"),_xlpm.art,IF(ISNUMBER(SEARCH(LEFT(_xlpm.t,1),"aeiou")),"an ","a "),E59&" is "&_xlpm.art&_xlpm.t&" from "&C59&" designed for application-specific laboratory, engineering or industrial use. It belongs to DIWAN's "&B59&" portfolio; final configuration must be selected against performance, integration and compliance requirements.")} -> ChroZen GC-VUV is a specialized gas chromatography product from Young In Chromass designed for application-specific laboratory, engineering or industrial use. It belongs to DIWAN's Gas Chromatography portfolio; final configuration must be selected against performance, integration and compliance requirements. | P59: ="Selection should confirm the model-specific operating range, capacity, accuracy, interfaces, utilities, accessories, standards, environmental limits and service requirements. Final capabilities depend on the approved "&E59&" configuration." -> Selection should confirm the model-specific operating range, capacity, accuracy, interfaces, utilities, accessories, standards, environmental limits and service requirements. Final capabilities depend on the approved ChroZen GC-VUV configuration. | R59: =B59&" applications; laboratory research, engineering development, quality control and industrial deployment where applicable. Suitability must be confirmed against the user's sample, process, environment and required standards." -> Gas Chromatography applications; laboratory research, engineering development, quality control and industrial deployment where applicable. Suitability must be confirmed against the user's sample, process, environment and required standards. | T59: =E59&" from "&C59 -> ChroZen GC-VUV from Young In Chromass | V59: No public downloadable document captured yet; provide the latest approved manufacturer document on request after revision and reuse checks. | W59: ="See other "&B59&" products" -> See other Gas Chromatography products | X59: =B59&" enquiry → website group enquiry form → category owner assignment" -> Gas Chromatography enquiry → website group enquiry form → category owner assignment | Y59: =E59&", "&B59&", "&C59&", technical equipment, DIWAN" -> ChroZen GC-VUV, Gas Chromatography, Young In Chromass, technical equipment, DIWAN | Z59: https://eng.youngincm.com/goods/list.php?M2_IDX=18659 | AA59: 46257 | AB59: Product Team / Technical Reviewer | AC59: =IF(AND(O59<>"",P59<>"",R59<>"",T59<>"",X59<>"",Y59<>"",Z59<>"",AA59<>"",AB59<>""),IF(AND(Q59<>"",S59<>"",U59<>""),"Ready for approval","Content drafted - assets/specs pending"),IF(COUNTA(O59:AB59)=0,"Not started","In progress")) -> Content drafted - assets/specs pending | AD59: ="Baseline definition created from the official catalog name, partner and category classification ("&G59&"). Model-specific specifications, images and downloadable documents must be extracted from the linked official source and technically approved before publication. Source register reviewed 2026-08-23." -> Baseline definition created from the official catalog name, partner and category classification (One page per product category). Model-specific specifications, images and downloadable documents must be extracted from the linked official source and technically approved before publication. Source register reviewed 2026-08-23. | AG59: Availability, configuration and commercial supply are subject to confirmation by DIWAN and the manufacturer. | AH59: Lead time is confirmed in the formal quotation; do not publish a fixed delivery commitment. | AI59: Publish manufacturer documents only when public access and reuse are permitted; otherwise provide controlled access on request.
A60: =IF(B60=B59,A59,A59+1) -> 11 | B60: Gas Generators | C60: Young In Chromass | D60: South Korea | E60: Whisper Nitrogen Generator (External Compressor) | F60: /products/gas-generators | G60: One page per product category | H60: 46257 | I60: Whisper Nitrogen Generator (External Compressor) | DIWAN Engineering & Technology Company | J60: whisper-nitrogen-generator-external-compressor | K60: =E60&" is "&IF(ISNUMBER(SEARCH(LEFT(LOWER(B60),1),"aeiou")),"an ","a ")&LOWER(B60)&" product from "&C60&" for application-specific laboratory, engineering or industrial use." -> Whisper Nitrogen Generator (External Compressor) is a gas generators product from Young In Chromass for application-specific laboratory, engineering or industrial use. | L60: =E60&" from "&C60&" for "&LOWER(B60)&" applications. Review configuration requirements and request technical information or a quotation from DIWAN." -> Whisper Nitrogen Generator (External Compressor) from Young In Chromass for gas generators applications. Review configuration requirements and request technical information or a quotation from DIWAN. | M60: Request technical information or a quote | N60: Baseline definition complete - official specifications and assets pending | O60: Whisper Nitrogen Generator (External Compressor) is a laboratory nitrogen gas generator from Young In Chromass for LC/MS supply and solvent-evaporation applications. Its configuration supports high-purity nitrogen delivery, pressure control and instrument gas integration; final capacity must be selected for the connected analyzer. | P60: High-purity nitrogen generation; external oil-free compressor configuration; internal storage tank; pressure control; system-status display; safety alarms; optional second nitrogen outlet. | Q60: Nitrogen purity: up to 99.999% for LC/MS configuration; pressure: up to 8 bar (115 psi); nitrogen flow: up to 64 L/min standard or 14 L/min LC/MS configuration; power: 230 VAC. | R60: LC/MS nitrogen supply, solvent evaporation, analytical laboratories and instrument gas support. | S60: https://cdn.nxcloud.biz/thumb/720/shop_product/0x0_5e8accea797d5.jpg | T60: =E60&" from "&C60 -> Whisper Nitrogen Generator (External Compressor) from Young In Chromass | V60: No public downloadable document captured yet; provide the latest approved manufacturer document on request after revision and reuse checks. | W60: ="See other "&B60&" products" -> See other Gas Generators products | X60: =B60&" enquiry → website group enquiry form → category owner assignment" -> Gas Generators enquiry → website group enquiry form → category owner assignment | Y60: =E60&", "&B60&", "&C60&", technical equipment, DIWAN" -> Whisper Nitrogen Generator (External Compressor), Gas Generators, Young In Chromass, technical equipment, DIWAN | Z60: https://eng.youngincm.com/goods/view.php?M2_IDX=18659&SC_BOOKMARK=N&SC_SF_IDX=Array&page=6&GS_IDX=20160 | AA60: 46257 | AB60: Product Team / Technical Reviewer | AC60: =IF(AND(O60<>"",P60<>"",R60<>"",T60<>"",X60<>"",Y60<>"",Z60<>"",AA60<>"",AB60<>""),IF(AND(Q60<>"",S60<>"",U60<>""),"Ready for approval","Content drafted - assets/specs pending"),IF(COUNTA(O60:AB60)=0,"Not started","In progress")) -> Content drafted - assets/specs pending | AD60: Exact official Young In Chromass product page verified for the Whisper nitrogen generator. Technical configuration and public assets require final product-team approval before publication. Source reviewed 2026-08-23. | AG60: Availability, configuration and commercial supply are subject to confirmation by DIWAN and the manufacturer. | AH60: Lead time is confirmed in the formal quotation; do not publish a fixed delivery commitment. | AI60: Publish manufacturer documents only when public access and reuse are permitted; otherwise provide controlled access on request.
A61: =IF(B61=B60,A60,A60+1) -> 11 | B61: Gas Generators | C61: Young In Chromass | D61: South Korea | E61: N2 Tower Plus (High Purity N2) Generator | F61: /products/gas-generators | G61: One page per product category | H61: 46257 | I61: N2 Tower Plus (High Purity N2) Generator | DIWAN Engineering & Technology Company | J61: n2-tower-plus-high-purity-n2-generator | K61: =E61&" is "&IF(ISNUMBER(SEARCH(LEFT(LOWER(B61),1),"aeiou")),"an ","a ")&LOWER(B61)&" product from "&C61&" for application-specific laboratory, engineering or industrial use." -> N2 Tower Plus (High Purity N2) Generator is a gas generators product from Young In Chromass for application-specific laboratory, engineering or industrial use. | L61: =E61&" from "&C61&" for "&LOWER(B61)&" applications. Review configuration requirements and request technical information or a quotation from DIWAN." -> N2 Tower Plus (High Purity N2) Generator from Young In Chromass for gas generators applications. Review configuration requirements and request technical information or a quotation from DIWAN. | M61: Request technical information or a quote | N61: Baseline definition complete - official specifications and assets pending | O61: {=_xlfn.LET(_xlpm.n,LOWER(E61),_xlpm.c,LOWER(B61),_xlpm.t,_xlfn.IFS(OR(ISNUMBER(SEARCH("lens",_xlpm.n)),ISNUMBER(SEARCH("optic",_xlpm.n)),ISNUMBER(SEARCH("polarizer",_xlpm.n))),"precision optical component",OR(ISNUMBER(SEARCH("camera",_xlpm.n)),ISNUMBER(SEARCH("imaging",_xlpm.n))),"scientific or industrial imaging system",ISNUMBER(SEARCH("pump",_xlpm.n)),"precision fluid-delivery system",OR(ISNUMBER(SEARCH("reactor",_xlpm.n)),ISNUMBER(SEARCH("autoclave",_xlpm.n)),ISNUMBER(SEARCH("pilot",_xlpm.n))),"laboratory or pilot-process system",OR(ISNUMBER(SEARCH("analyzer",_xlpm.n)),ISNUMBER(SEARCH("spectrometer",_xlpm.n)),ISNUMBER(SEARCH("hplc",_xlpm.n)),ISNUMBER(SEARCH("chrom",_xlpm.n))),"analytical laboratory instrument",OR(ISNUMBER(SEARCH("tester",_xlpm.n)),ISNUMBER(SEARCH("testing machine",_xlpm.n)),ISNUMBER(SEARCH("chamber",_xlpm.n))),"materials or component testing system",OR(ISNUMBER(SEARCH("sensor",_xlpm.n)),ISNUMBER(SEARCH("terminal",_xlpm.n)),ISNUMBER(SEARCH("station",_xlpm.n)),ISNUMBER(SEARCH("satellite",_xlpm.n))),"space or sensing subsystem",ISNUMBER(SEARCH("software",_xlpm.n)),"specialized engineering software platform",TRUE,"specialized "&_xlpm.c&" product"),_xlpm.art,IF(ISNUMBER(SEARCH(LEFT(_xlpm.t,1),"aeiou")),"an ","a "),E61&" is "&_xlpm.art&_xlpm.t&" from "&C61&" designed for application-specific laboratory, engineering or industrial use. It belongs to DIWAN's "&B61&" portfolio; final configuration must be selected against performance, integration and compliance requirements.")} -> N2 Tower Plus (High Purity N2) Generator is a specialized gas generators product from Young In Chromass designed for application-specific laboratory, engineering or industrial use. It belongs to DIWAN's Gas Generators portfolio; final configuration must be selected against performance, integration and compliance requirements. | P61: ="Selection should confirm the model-specific operating range, capacity, accuracy, interfaces, utilities, accessories, standards, environmental limits and service requirements. Final capabilities depend on the approved "&E61&" configuration." -> Selection should confirm the model-specific operating range, capacity, accuracy, interfaces, utilities, accessories, standards, environmental limits and service requirements. Final capabilities depend on the approved N2 Tower Plus (High Purity N2) Generator configuration. | R61: =B61&" applications; laboratory research, engineering development, quality control and industrial deployment where applicable. Suitability must be confirmed against the user's sample, process, environment and required standards." -> Gas Generators applications; laboratory research, engineering development, quality control and industrial deployment where applicable. Suitability must be confirmed against the user's sample, process, environment and required standards. | S61: https://cdn.nxcloud.biz/thumb/720/shop_product/0x0_5e8aa7621b9a3.jpg | T61: =E61&" from "&C61 -> N2 Tower Plus (High Purity N2) Generator from Young In Chromass | V61: No public downloadable document captured yet; provide the latest approved manufacturer document on request after revision and reuse checks. | W61: ="See other "&B61&" products" -> See other Gas Generators products | X61: =B61&" enquiry → website group enquiry form → category owner assignment" -> Gas Generators enquiry → website group enquiry form → category owner assignment | Y61: =E61&", "&B61&", "&C61&", technical equipment, DIWAN" -> N2 Tower Plus (High Purity N2) Generator, Gas Generators, Young In Chromass, technical equipment, DIWAN | Z61: https://eng.youngincm.com/goods/read.php?M2_IDX=18462&SC_BOOKMARK=N&SC_SC1_IDX=406&SC_SF_IDX=Array&SP_CODE=2306OKKA | AA61: 46257 | AB61: Product Team / Technical Reviewer | AC61: =IF(AND(O61<>"",P61<>"",R61<>"",T61<>"",X61<>"",Y61<>"",Z61<>"",AA61<>"",AB61<>""),IF(AND(Q61<>"",S61<>"",U61<>""),"Ready for approval","Content drafted - assets/specs pending"),IF(COUNTA(O61:AB61)=0,"Not started","In progress")) -> Content drafted - assets/specs pending | AD61: ="Baseline definition created from the official catalog name, partner and category classification ("&G61&"). Model-specific specifications, images and downloadable documents must be extracted from the linked official source and technically approved before publication. Source register reviewed 2026-08-23." -> Baseline definition created from the official catalog name, partner and category classification (One page per product category). Model-specific specifications, images and downloadable documents must be extracted from the linked official source and technically approved before publication. Source register reviewed 2026-08-23. | AG61: Availability, configuration and commercial supply are subject to confirmation by DIWAN and the manufacturer. | AH61: Lead time is confirmed in the formal quotation; do not publish a fixed delivery commitment. | AI61: Publish manufacturer documents only when public access and reuse are permitted; otherwise provide controlled access on request.
A62: =IF(B62=B61,A61,A61+1) -> 11 | B62: Gas Generators | C62: Young In Chromass | D62: South Korea | E62: Air Ultra Zero Generator (Hydrocarbon Trap Type) | F62: /products/gas-generators | G62: One page per product category | H62: 46257 | I62: Air Ultra Zero Generator (Hydrocarbon Trap Type) | DIWAN Engineering & Technology Company | J62: air-ultra-zero-generator-hydrocarbon-trap | K62: =E62&" is "&IF(ISNUMBER(SEARCH(LEFT(LOWER(B62),1),"aeiou")),"an ","a ")&LOWER(B62)&" product from "&C62&" for application-specific laboratory, engineering or industrial use." -> Air Ultra Zero Generator (Hydrocarbon Trap Type) is a gas generators product from Young In Chromass for application-specific laboratory, engineering or industrial use. | L62: =E62&" from "&C62&" for "&LOWER(B62)&" applications. Review configuration requirements and request technical information or a quotation from DIWAN." -> Air Ultra Zero Generator (Hydrocarbon Trap Type) from Young In Chromass for gas generators applications. Review configuration requirements and request technical information or a quotation from DIWAN. | M62: Request technical information or a quote | N62: Baseline definition complete - official specifications and assets pending | O62: {=_xlfn.LET(_xlpm.n,LOWER(E62),_xlpm.c,LOWER(B62),_xlpm.t,_xlfn.IFS(OR(ISNUMBER(SEARCH("lens",_xlpm.n)),ISNUMBER(SEARCH("optic",_xlpm.n)),ISNUMBER(SEARCH("polarizer",_xlpm.n))),"precision optical component",OR(ISNUMBER(SEARCH("camera",_xlpm.n)),ISNUMBER(SEARCH("imaging",_xlpm.n))),"scientific or industrial imaging system",ISNUMBER(SEARCH("pump",_xlpm.n)),"precision fluid-delivery system",OR(ISNUMBER(SEARCH("reactor",_xlpm.n)),ISNUMBER(SEARCH("autoclave",_xlpm.n)),ISNUMBER(SEARCH("pilot",_xlpm.n))),"laboratory or pilot-process system",OR(ISNUMBER(SEARCH("analyzer",_xlpm.n)),ISNUMBER(SEARCH("spectrometer",_xlpm.n)),ISNUMBER(SEARCH("hplc",_xlpm.n)),ISNUMBER(SEARCH("chrom",_xlpm.n))),"analytical laboratory instrument",OR(ISNUMBER(SEARCH("tester",_xlpm.n)),ISNUMBER(SEARCH("testing machine",_xlpm.n)),ISNUMBER(SEARCH("chamber",_xlpm.n))),"materials or component testing system",OR(ISNUMBER(SEARCH("sensor",_xlpm.n)),ISNUMBER(SEARCH("terminal",_xlpm.n)),ISNUMBER(SEARCH("station",_xlpm.n)),ISNUMBER(SEARCH("satellite",_xlpm.n))),"space or sensing subsystem",ISNUMBER(SEARCH("software",_xlpm.n)),"specialized engineering software platform",TRUE,"specialized "&_xlpm.c&" product"),_xlpm.art,IF(ISNUMBER(SEARCH(LEFT(_xlpm.t,1),"aeiou")),"an ","a "),E62&" is "&_xlpm.art&_xlpm.t&" from "&C62&" designed for application-specific laboratory, engineering or industrial use. It belongs to DIWAN's "&B62&" portfolio; final configuration must be selected against performance, integration and compliance requirements.")} -> Air Ultra Zero Generator (Hydrocarbon Trap Type) is a specialized gas generators product from Young In Chromass designed for application-specific laboratory, engineering or industrial use. It belongs to DIWAN's Gas Generators portfolio; final configuration must be selected against performance, integration and compliance requirements. | P62: ="Selection should confirm the model-specific operating range, capacity, accuracy, interfaces, utilities, accessories, standards, environmental limits and service requirements. Final capabilities depend on the approved "&E62&" configuration." -> Selection should confirm the model-specific operating range, capacity, accuracy, interfaces, utilities, accessories, standards, environmental limits and service requirements. Final capabilities depend on the approved Air Ultra Zero Generator (Hydrocarbon Trap Type) configuration. | R62: =B62&" applications; laboratory research, engineering development, quality control and industrial deployment where applicable. Suitability must be confirmed against the user's sample, process, environment and required standards." -> Gas Generators applications; laboratory research, engineering development, quality control and industrial deployment where applicable. Suitability must be confirmed against the user's sample, process, environment and required standards. | S62: https://cdn.nxcloud.biz/thumb/720/shop_product/0x0_5e8a9024c2997.jpg | T62: =E62&" from "&C62 -> Air Ultra Zero Generator (Hydrocarbon Trap Type) from Young In Chromass | V62: No public downloadable document captured yet; provide the latest approved manufacturer document on request after revision and reuse checks. | W62: ="See other "&B62&" products" -> See other Gas Generators products | X62: =B62&" enquiry → website group enquiry form → category owner assignment" -> Gas Generators enquiry → website group enquiry form → category owner assignment | Y62: =E62&", "&B62&", "&C62&", technical equipment, DIWAN" -> Air Ultra Zero Generator (Hydrocarbon Trap Type), Gas Generators, Young In Chromass, technical equipment, DIWAN | Z62: https://eng.youngincm.com/goods/read.php?M2_IDX=18462&SC_BOOKMARK=N&SC_SC1_IDX=406&SC_SF_IDX=Array&SP_CODE=2004BVPH | AA62: 46257 | AB62: Product Team / Technical Reviewer | AC62: =IF(AND(O62<>"",P62<>"",R62<>"",T62<>"",X62<>"",Y62<>"",Z62<>"",AA62<>"",AB62<>""),IF(AND(Q62<>"",S62<>"",U62<>""),"Ready for approval","Content drafted - assets/specs pending"),IF(COUNTA(O62:AB62)=0,"Not started","In progress")) -> Content drafted - assets/specs pending | AD62: ="Baseline definition created from the official catalog name, partner and category classification ("&G62&"). Model-specific specifications, images and downloadable documents must be extracted from the linked official source and technically approved before publication. Source register reviewed 2026-08-23." -> Baseline definition created from the official catalog name, partner and category classification (One page per product category). Model-specific specifications, images and downloadable documents must be extracted from the linked official source and technically approved before publication. Source register reviewed 2026-08-23. | AG62: Availability, configuration and commercial supply are subject to confirmation by DIWAN and the manufacturer. | AH62: Lead time is confirmed in the formal quotation; do not publish a fixed delivery commitment. | AI62: Publish manufacturer documents only when public access and reuse are permitted; otherwise provide controlled access on request.
A63: =IF(B63=B62,A62,A62+1) -> 11 | B63: Gas Generators | C63: Young In Chromass | D63: South Korea | E63: Air Generator (Zero Air GC Series) | F63: /products/gas-generators | G63: One page per product category | H63: 46257 | I63: Air Generator (Zero Air GC Series) | DIWAN Engineering & Technology Company | J63: air-generator-zero-air-gc-series | K63: =E63&" is "&IF(ISNUMBER(SEARCH(LEFT(LOWER(B63),1),"aeiou")),"an ","a ")&LOWER(B63)&" product from "&C63&" for application-specific laboratory, engineering or industrial use." -> Air Generator (Zero Air GC Series) is a gas generators product from Young In Chromass for application-specific laboratory, engineering or industrial use. | L63: =E63&" from "&C63&" for "&LOWER(B63)&" applications. Review configuration requirements and request technical information or a quotation from DIWAN." -> Air Generator (Zero Air GC Series) from Young In Chromass for gas generators applications. Review configuration requirements and request technical information or a quotation from DIWAN. | M63: Request technical information or a quote | N63: Baseline definition complete - official specifications and assets pending | O63: {=_xlfn.LET(_xlpm.n,LOWER(E63),_xlpm.c,LOWER(B63),_xlpm.t,_xlfn.IFS(OR(ISNUMBER(SEARCH("lens",_xlpm.n)),ISNUMBER(SEARCH("optic",_xlpm.n)),ISNUMBER(SEARCH("polarizer",_xlpm.n))),"precision optical component",OR(ISNUMBER(SEARCH("camera",_xlpm.n)),ISNUMBER(SEARCH("imaging",_xlpm.n))),"scientific or industrial imaging system",ISNUMBER(SEARCH("pump",_xlpm.n)),"precision fluid-delivery system",OR(ISNUMBER(SEARCH("reactor",_xlpm.n)),ISNUMBER(SEARCH("autoclave",_xlpm.n)),ISNUMBER(SEARCH("pilot",_xlpm.n))),"laboratory or pilot-process system",OR(ISNUMBER(SEARCH("analyzer",_xlpm.n)),ISNUMBER(SEARCH("spectrometer",_xlpm.n)),ISNUMBER(SEARCH("hplc",_xlpm.n)),ISNUMBER(SEARCH("chrom",_xlpm.n))),"analytical laboratory instrument",OR(ISNUMBER(SEARCH("tester",_xlpm.n)),ISNUMBER(SEARCH("testing machine",_xlpm.n)),ISNUMBER(SEARCH("chamber",_xlpm.n))),"materials or component testing system",OR(ISNUMBER(SEARCH("sensor",_xlpm.n)),ISNUMBER(SEARCH("terminal",_xlpm.n)),ISNUMBER(SEARCH("station",_xlpm.n)),ISNUMBER(SEARCH("satellite",_xlpm.n))),"space or sensing subsystem",ISNUMBER(SEARCH("software",_xlpm.n)),"specialized engineering software platform",TRUE,"specialized "&_xlpm.c&" product"),_xlpm.art,IF(ISNUMBER(SEARCH(LEFT(_xlpm.t,1),"aeiou")),"an ","a "),E63&" is "&_xlpm.art&_xlpm.t&" from "&C63&" designed for application-specific laboratory, engineering or industrial use. It belongs to DIWAN's "&B63&" portfolio; final configuration must be selected against performance, integration and compliance requirements.")} -> Air Generator (Zero Air GC Series) is a specialized gas generators product from Young In Chromass designed for application-specific laboratory, engineering or industrial use. It belongs to DIWAN's Gas Generators portfolio; final configuration must be selected against performance, integration and compliance requirements. | P63: ="Selection should confirm the model-specific operating range, capacity, accuracy, interfaces, utilities, accessories, standards, environmental limits and service requirements. Final capabilities depend on the approved "&E63&" configuration." -> Selection should confirm the model-specific operating range, capacity, accuracy, interfaces, utilities, accessories, standards, environmental limits and service requirements. Final capabilities depend on the approved Air Generator (Zero Air GC Series) configuration. | R63: =B63&" applications; laboratory research, engineering development, quality control and industrial deployment where applicable. Suitability must be confirmed against the user's sample, process, environment and required standards." -> Gas Generators applications; laboratory research, engineering development, quality control and industrial deployment where applicable. Suitability must be confirmed against the user's sample, process, environment and required standards. | S63: https://cdn.nxcloud.biz/thumb/720/shop_product/0x0_5e8a9244f7291.jpg | T63: =E63&" from "&C63 -> Air Generator (Zero Air GC Series) from Young In Chromass | V63: No public downloadable document captured yet; provide the latest approved manufacturer document on request after revision and reuse checks. | W63: ="See other "&B63&" products" -> See other Gas Generators products | X63: =B63&" enquiry → website group enquiry form → category owner assignment" -> Gas Generators enquiry → website group enquiry form → category owner assignment | Y63: =E63&", "&B63&", "&C63&", technical equipment, DIWAN" -> Air Generator (Zero Air GC Series), Gas Generators, Young In Chromass, technical equipment, DIWAN | Z63: https://eng.youngincm.com/goods/read.php?M2_IDX=18462&SC_BOOKMARK=N&SC_SC1_IDX=406&SC_SF_IDX=Array&SP_CODE=2004TOGJ | AA63: 46257 | AB63: Product Team / Technical Reviewer | AC63: =IF(AND(O63<>"",P63<>"",R63<>"",T63<>"",X63<>"",Y63<>"",Z63<>"",AA63<>"",AB63<>""),IF(AND(Q63<>"",S63<>"",U63<>""),"Ready for approval","Content drafted - assets/specs pending"),IF(COUNTA(O63:AB63)=0,"Not started","In progress")) -> Content drafted - assets/specs pending | AD63: ="Baseline definition created from the official catalog name, partner and category classification ("&G63&"). Model-specific specifications, images and downloadable documents must be extracted from the linked official source and technically approved before publication. Source register reviewed 2026-08-23." -> Baseline definition created from the official catalog name, partner and category classification (One page per product category). Model-specific specifications, images and downloadable documents must be extracted from the linked official source and technically approved before publication. Source register reviewed 2026-08-23. | AG63: Availability, configuration and commercial supply are subject to confirmation by DIWAN and the manufacturer. | AH63: Lead time is confirmed in the formal quotation; do not publish a fixed delivery commitment. | AI63: Publish manufacturer documents only when public access and reuse are permitted; otherwise provide controlled access on request.
A64: =IF(B64=B63,A63,A63+1) -> 11 | B64: Gas Generators | C64: Young In Chromass | D64: South Korea | E64: Mistral Evolution (Built-in Compressor) | F64: /products/gas-generators | G64: One page per product category | H64: 46257 | I64: Mistral Evolution (Built-in Compressor) | DIWAN Engineering & Technology Company | J64: mistral-evolution-built-in-compressor | K64: =E64&" is "&IF(ISNUMBER(SEARCH(LEFT(LOWER(B64),1),"aeiou")),"an ","a ")&LOWER(B64)&" product from "&C64&" for application-specific laboratory, engineering or industrial use." -> Mistral Evolution (Built-in Compressor) is a gas generators product from Young In Chromass for application-specific laboratory, engineering or industrial use. | L64: =E64&" from "&C64&" for "&LOWER(B64)&" applications. Review configuration requirements and request technical information or a quotation from DIWAN." -> Mistral Evolution (Built-in Compressor) from Young In Chromass for gas generators applications. Review configuration requirements and request technical information or a quotation from DIWAN. | M64: Request technical information or a quote | N64: Baseline definition complete - official specifications and assets pending | O64: {=_xlfn.LET(_xlpm.n,LOWER(E64),_xlpm.c,LOWER(B64),_xlpm.t,_xlfn.IFS(OR(ISNUMBER(SEARCH("lens",_xlpm.n)),ISNUMBER(SEARCH("optic",_xlpm.n)),ISNUMBER(SEARCH("polarizer",_xlpm.n))),"precision optical component",OR(ISNUMBER(SEARCH("camera",_xlpm.n)),ISNUMBER(SEARCH("imaging",_xlpm.n))),"scientific or industrial imaging system",ISNUMBER(SEARCH("pump",_xlpm.n)),"precision fluid-delivery system",OR(ISNUMBER(SEARCH("reactor",_xlpm.n)),ISNUMBER(SEARCH("autoclave",_xlpm.n)),ISNUMBER(SEARCH("pilot",_xlpm.n))),"laboratory or pilot-process system",OR(ISNUMBER(SEARCH("analyzer",_xlpm.n)),ISNUMBER(SEARCH("spectrometer",_xlpm.n)),ISNUMBER(SEARCH("hplc",_xlpm.n)),ISNUMBER(SEARCH("chrom",_xlpm.n))),"analytical laboratory instrument",OR(ISNUMBER(SEARCH("tester",_xlpm.n)),ISNUMBER(SEARCH("testing machine",_xlpm.n)),ISNUMBER(SEARCH("chamber",_xlpm.n))),"materials or component testing system",OR(ISNUMBER(SEARCH("sensor",_xlpm.n)),ISNUMBER(SEARCH("terminal",_xlpm.n)),ISNUMBER(SEARCH("station",_xlpm.n)),ISNUMBER(SEARCH("satellite",_xlpm.n))),"space or sensing subsystem",ISNUMBER(SEARCH("software",_xlpm.n)),"specialized engineering software platform",TRUE,"specialized "&_xlpm.c&" product"),_xlpm.art,IF(ISNUMBER(SEARCH(LEFT(_xlpm.t,1),"aeiou")),"an ","a "),E64&" is "&_xlpm.art&_xlpm.t&" from "&C64&" designed for application-specific laboratory, engineering or industrial use. It belongs to DIWAN's "&B64&" portfolio; final configuration must be selected against performance, integration and compliance requirements.")} -> Mistral Evolution (Built-in Compressor) is a specialized gas generators product from Young In Chromass designed for application-specific laboratory, engineering or industrial use. It belongs to DIWAN's Gas Generators portfolio; final configuration must be selected against performance, integration and compliance requirements. | P64: ="Selection should confirm the model-specific operating range, capacity, accuracy, interfaces, utilities, accessories, standards, environmental limits and service requirements. Final capabilities depend on the approved "&E64&" configuration." -> Selection should confirm the model-specific operating range, capacity, accuracy, interfaces, utilities, accessories, standards, environmental limits and service requirements. Final capabilities depend on the approved Mistral Evolution (Built-in Compressor) configuration. | R64: =B64&" applications; laboratory research, engineering development, quality control and industrial deployment where applicable. Suitability must be confirmed against the user's sample, process, environment and required standards." -> Gas Generators applications; laboratory research, engineering development, quality control and industrial deployment where applicable. Suitability must be confirmed against the user's sample, process, environment and required standards. | S64: https://cdn.nxcloud.biz/thumb/720/shop_product/0x0_5e8acbe45f6cb.jpg | T64: =E64&" from "&C64 -> Mistral Evolution (Built-in Compressor) from Young In Chromass | V64: No public downloadable document captured yet; provide the latest approved manufacturer document on request after revision and reuse checks. | W64: ="See other "&B64&" products" -> See other Gas Generators products | X64: =B64&" enquiry → website group enquiry form → category owner assignment" -> Gas Generators enquiry → website group enquiry form → category owner assignment | Y64: =E64&", "&B64&", "&C64&", technical equipment, DIWAN" -> Mistral Evolution (Built-in Compressor), Gas Generators, Young In Chromass, technical equipment, DIWAN | Z64: https://eng.youngincm.com/goods/read.php?M2_IDX=18462&SC_BOOKMARK=N&SC_SC1_IDX=406&SC_SF_IDX=Array&SP_CODE=2305NROA | AA64: 46257 | AB64: Product Team / Technical Reviewer | AC64: =IF(AND(O64<>"",P64<>"",R64<>"",T64<>"",X64<>"",Y64<>"",Z64<>"",AA64<>"",AB64<>""),IF(AND(Q64<>"",S64<>"",U64<>""),"Ready for approval","Content drafted - assets/specs pending"),IF(COUNTA(O64:AB64)=0,"Not started","In progress")) -> Content drafted - assets/specs pending | AD64: ="Baseline definition created from the official catalog name, partner and category classification ("&G64&"). Model-specific specifications, images and downloadable documents must be extracted from the linked official source and technically approved before publication. Source register reviewed 2026-08-23." -> Baseline definition created from the official catalog name, partner and category classification (One page per product category). Model-specific specifications, images and downloadable documents must be extracted from the linked official source and technically approved before publication. Source register reviewed 2026-08-23. | AG64: Availability, configuration and commercial supply are subject to confirmation by DIWAN and the manufacturer. | AH64: Lead time is confirmed in the formal quotation; do not publish a fixed delivery commitment. | AI64: Publish manufacturer documents only when public access and reuse are permitted; otherwise provide controlled access on request.
A65: =IF(B65=B64,A64,A64+1) -> 12 | B65: Ion Chromatography | C65: Young In Chromass | D65: South Korea | E65: ChroZen IC Modules | F65: /products/ion-chromatography | G65: One page per product category | H65: 46257 | I65: ChroZen IC Modules | DIWAN Engineering & Technology Company | J65: chrozen-ic-modules | K65: =E65&" is "&IF(ISNUMBER(SEARCH(LEFT(LOWER(B65),1),"aeiou")),"an ","a ")&LOWER(B65)&" product from "&C65&" for application-specific laboratory, engineering or industrial use." -> ChroZen IC Modules is an ion chromatography product from Young In Chromass for application-specific laboratory, engineering or industrial use. | L65: =E65&" from "&C65&" for "&LOWER(B65)&" applications. Review configuration requirements and request technical information or a quotation from DIWAN." -> ChroZen IC Modules from Young In Chromass for ion chromatography applications. Review configuration requirements and request technical information or a quotation from DIWAN. | M65: Request technical information or a quote | N65: Baseline definition complete - official specifications and assets pending | O65: {=_xlfn.LET(_xlpm.n,LOWER(E65),_xlpm.c,LOWER(B65),_xlpm.t,_xlfn.IFS(OR(ISNUMBER(SEARCH("lens",_xlpm.n)),ISNUMBER(SEARCH("optic",_xlpm.n)),ISNUMBER(SEARCH("polarizer",_xlpm.n))),"precision optical component",OR(ISNUMBER(SEARCH("camera",_xlpm.n)),ISNUMBER(SEARCH("imaging",_xlpm.n))),"scientific or industrial imaging system",ISNUMBER(SEARCH("pump",_xlpm.n)),"precision fluid-delivery system",OR(ISNUMBER(SEARCH("reactor",_xlpm.n)),ISNUMBER(SEARCH("autoclave",_xlpm.n)),ISNUMBER(SEARCH("pilot",_xlpm.n))),"laboratory or pilot-process system",OR(ISNUMBER(SEARCH("analyzer",_xlpm.n)),ISNUMBER(SEARCH("spectrometer",_xlpm.n)),ISNUMBER(SEARCH("hplc",_xlpm.n)),ISNUMBER(SEARCH("chrom",_xlpm.n))),"analytical laboratory instrument",OR(ISNUMBER(SEARCH("tester",_xlpm.n)),ISNUMBER(SEARCH("testing machine",_xlpm.n)),ISNUMBER(SEARCH("chamber",_xlpm.n))),"materials or component testing system",OR(ISNUMBER(SEARCH("sensor",_xlpm.n)),ISNUMBER(SEARCH("terminal",_xlpm.n)),ISNUMBER(SEARCH("station",_xlpm.n)),ISNUMBER(SEARCH("satellite",_xlpm.n))),"space or sensing subsystem",ISNUMBER(SEARCH("software",_xlpm.n)),"specialized engineering software platform",TRUE,"specialized "&_xlpm.c&" product"),_xlpm.art,IF(ISNUMBER(SEARCH(LEFT(_xlpm.t,1),"aeiou")),"an ","a "),E65&" is "&_xlpm.art&_xlpm.t&" from "&C65&" designed for application-specific laboratory, engineering or industrial use. It belongs to DIWAN's "&B65&" portfolio; final configuration must be selected against performance, integration and compliance requirements.")} -> ChroZen IC Modules is a specialized ion chromatography product from Young In Chromass designed for application-specific laboratory, engineering or industrial use. It belongs to DIWAN's Ion Chromatography portfolio; final configuration must be selected against performance, integration and compliance requirements. | P65: ="Selection should confirm the model-specific operating range, capacity, accuracy, interfaces, utilities, accessories, standards, environmental limits and service requirements. Final capabilities depend on the approved "&E65&" configuration." -> Selection should confirm the model-specific operating range, capacity, accuracy, interfaces, utilities, accessories, standards, environmental limits and service requirements. Final capabilities depend on the approved ChroZen IC Modules configuration. | R65: =B65&" applications; laboratory research, engineering development, quality control and industrial deployment where applicable. Suitability must be confirmed against the user's sample, process, environment and required standards." -> Ion Chromatography applications; laboratory research, engineering development, quality control and industrial deployment where applicable. Suitability must be confirmed against the user's sample, process, environment and required standards. | T65: =E65&" from "&C65 -> ChroZen IC Modules from Young In Chromass | V65: No public downloadable document captured yet; provide the latest approved manufacturer document on request after revision and reuse checks. | W65: ="See other "&B65&" products" -> See other Ion Chromatography products | X65: =B65&" enquiry → website group enquiry form → category owner assignment" -> Ion Chromatography enquiry → website group enquiry form → category owner assignment | Y65: =E65&", "&B65&", "&C65&", technical equipment, DIWAN" -> ChroZen IC Modules, Ion Chromatography, Young In Chromass, technical equipment, DIWAN | Z65: https://eng.youngincm.com/goods/list.php?M2_IDX=18659 | AA65: 46257 | AB65: Product Team / Technical Reviewer | AC65: =IF(AND(O65<>"",P65<>"",R65<>"",T65<>"",X65<>"",Y65<>"",Z65<>"",AA65<>"",AB65<>""),IF(AND(Q65<>"",S65<>"",U65<>""),"Ready for approval","Content drafted - assets/specs pending"),IF(COUNTA(O65:AB65)=0,"Not started","In progress")) -> Content drafted - assets/specs pending | AD65: ="Baseline definition created from the official catalog name, partner and category classification ("&G65&"). Model-specific specifications, images and downloadable documents must be extracted from the linked official source and technically approved before publication. Source register reviewed 2026-08-23." -> Baseline definition created from the official catalog name, partner and category classification (One page per product category). Model-specific specifications, images and downloadable documents must be extracted from the linked official source and technically approved before publication. Source register reviewed 2026-08-23. | AG65: Availability, configuration and commercial supply are subject to confirmation by DIWAN and the manufacturer. | AH65: Lead time is confirmed in the formal quotation; do not publish a fixed delivery commitment. | AI65: Publish manufacturer documents only when public access and reuse are permitted; otherwise provide controlled access on request.
A66: =IF(B66=B65,A65,A65+1) -> 12 | B66: Ion Chromatography | C66: Young In Chromass | D66: South Korea | E66: ChroZen IC Consumables (Columns & Suppressors) | F66: /products/ion-chromatography | G66: One page per product category | H66: 46257 | I66: ChroZen IC Consumables (Columns & Suppressors) | DIWAN Engineering & Technology Company | J66: chrozen-ic-consumables-columns-and-suppressors | K66: =E66&" is "&IF(ISNUMBER(SEARCH(LEFT(LOWER(B66),1),"aeiou")),"an ","a ")&LOWER(B66)&" product from "&C66&" for application-specific laboratory, engineering or industrial use." -> ChroZen IC Consumables (Columns & Suppressors) is an ion chromatography product from Young In Chromass for application-specific laboratory, engineering or industrial use. | L66: =E66&" from "&C66&" for "&LOWER(B66)&" applications. Review configuration requirements and request technical information or a quotation from DIWAN." -> ChroZen IC Consumables (Columns & Suppressors) from Young In Chromass for ion chromatography applications. Review configuration requirements and request technical information or a quotation from DIWAN. | M66: Request technical information or a quote | N66: Baseline definition complete - official specifications and assets pending | O66: {=_xlfn.LET(_xlpm.n,LOWER(E66),_xlpm.c,LOWER(B66),_xlpm.t,_xlfn.IFS(OR(ISNUMBER(SEARCH("lens",_xlpm.n)),ISNUMBER(SEARCH("optic",_xlpm.n)),ISNUMBER(SEARCH("polarizer",_xlpm.n))),"precision optical component",OR(ISNUMBER(SEARCH("camera",_xlpm.n)),ISNUMBER(SEARCH("imaging",_xlpm.n))),"scientific or industrial imaging system",ISNUMBER(SEARCH("pump",_xlpm.n)),"precision fluid-delivery system",OR(ISNUMBER(SEARCH("reactor",_xlpm.n)),ISNUMBER(SEARCH("autoclave",_xlpm.n)),ISNUMBER(SEARCH("pilot",_xlpm.n))),"laboratory or pilot-process system",OR(ISNUMBER(SEARCH("analyzer",_xlpm.n)),ISNUMBER(SEARCH("spectrometer",_xlpm.n)),ISNUMBER(SEARCH("hplc",_xlpm.n)),ISNUMBER(SEARCH("chrom",_xlpm.n))),"analytical laboratory instrument",OR(ISNUMBER(SEARCH("tester",_xlpm.n)),ISNUMBER(SEARCH("testing machine",_xlpm.n)),ISNUMBER(SEARCH("chamber",_xlpm.n))),"materials or component testing system",OR(ISNUMBER(SEARCH("sensor",_xlpm.n)),ISNUMBER(SEARCH("terminal",_xlpm.n)),ISNUMBER(SEARCH("station",_xlpm.n)),ISNUMBER(SEARCH("satellite",_xlpm.n))),"space or sensing subsystem",ISNUMBER(SEARCH("software",_xlpm.n)),"specialized engineering software platform",TRUE,"specialized "&_xlpm.c&" product"),_xlpm.art,IF(ISNUMBER(SEARCH(LEFT(_xlpm.t,1),"aeiou")),"an ","a "),E66&" is "&_xlpm.art&_xlpm.t&" from "&C66&" designed for application-specific laboratory, engineering or industrial use. It belongs to DIWAN's "&B66&" portfolio; final configuration must be selected against performance, integration and compliance requirements.")} -> ChroZen IC Consumables (Columns & Suppressors) is a specialized ion chromatography product from Young In Chromass designed for application-specific laboratory, engineering or industrial use. It belongs to DIWAN's Ion Chromatography portfolio; final configuration must be selected against performance, integration and compliance requirements. | P66: ="Selection should confirm the model-specific operating range, capacity, accuracy, interfaces, utilities, accessories, standards, environmental limits and service requirements. Final capabilities depend on the approved "&E66&" configuration." -> Selection should confirm the model-specific operating range, capacity, accuracy, interfaces, utilities, accessories, standards, environmental limits and service requirements. Final capabilities depend on the approved ChroZen IC Consumables (Columns & Suppressors) configuration. | R66: =B66&" applications; laboratory research, engineering development, quality control and industrial deployment where applicable. Suitability must be confirmed against the user's sample, process, environment and required standards." -> Ion Chromatography applications; laboratory research, engineering development, quality control and industrial deployment where applicable. Suitability must be confirmed against the user's sample, process, environment and required standards. | T66: =E66&" from "&C66 -> ChroZen IC Consumables (Columns & Suppressors) from Young In Chromass | V66: No public downloadable document captured yet; provide the latest approved manufacturer document on request after revision and reuse checks. | W66: ="See other "&B66&" products" -> See other Ion Chromatography products | X66: =B66&" enquiry → website group enquiry form → category owner assignment" -> Ion Chromatography enquiry → website group enquiry form → category owner assignment | Y66: =E66&", "&B66&", "&C66&", technical equipment, DIWAN" -> ChroZen IC Consumables (Columns & Suppressors), Ion Chromatography, Young In Chromass, technical equipment, DIWAN | Z66: https://eng.youngincm.com/goods/list.php?M2_IDX=18659 | AA66: 46257 | AB66: Product Team / Technical Reviewer | AC66: =IF(AND(O66<>"",P66<>"",R66<>"",T66<>"",X66<>"",Y66<>"",Z66<>"",AA66<>"",AB66<>""),IF(AND(Q66<>"",S66<>"",U66<>""),"Ready for approval","Content drafted - assets/specs pending"),IF(COUNTA(O66:AB66)=0,"Not started","In progress")) -> Content drafted - assets/specs pending | AD66: ="Baseline definition created from the official catalog name, partner and category classification ("&G66&"). Model-specific specifications, images and downloadable documents must be extracted from the linked official source and technically approved before publication. Source register reviewed 2026-08-23." -> Baseline definition created from the official catalog name, partner and category classification (One page per product category). Model-specific specifications, images and downloadable documents must be extracted from the linked official source and technically approved before publication. Source register reviewed 2026-08-23. | AG66: Availability, configuration and commercial supply are subject to confirmation by DIWAN and the manufacturer. | AH66: Lead time is confirmed in the formal quotation; do not publish a fixed delivery commitment. | AI66: Publish manufacturer documents only when public access and reuse are permitted; otherwise provide controlled access on request.
A67: =IF(B67=B66,A66,A66+1) -> 13 | B67: Liquid Chromatography | C67: Young In Chromass | D67: South Korea | E67: ChroZen HPLC | F67: /products/liquid-chromatography | G67: One page per product category | H67: 46257 | I67: ChroZen HPLC | DIWAN Engineering & Technology Company | J67: chrozen-hplc | K67: =E67&" is "&IF(ISNUMBER(SEARCH(LEFT(LOWER(B67),1),"aeiou")),"an ","a ")&LOWER(B67)&" product from "&C67&" for application-specific laboratory, engineering or industrial use." -> ChroZen HPLC is a liquid chromatography product from Young In Chromass for application-specific laboratory, engineering or industrial use. | L67: =E67&" from "&C67&" for "&LOWER(B67)&" applications. Review configuration requirements and request technical information or a quotation from DIWAN." -> ChroZen HPLC from Young In Chromass for liquid chromatography applications. Review configuration requirements and request technical information or a quotation from DIWAN. | M67: Request technical information or a quote | N67: Baseline definition complete - official specifications and assets pending | O67: {=_xlfn.LET(_xlpm.n,LOWER(E67),_xlpm.c,LOWER(B67),_xlpm.t,_xlfn.IFS(OR(ISNUMBER(SEARCH("lens",_xlpm.n)),ISNUMBER(SEARCH("optic",_xlpm.n)),ISNUMBER(SEARCH("polarizer",_xlpm.n))),"precision optical component",OR(ISNUMBER(SEARCH("camera",_xlpm.n)),ISNUMBER(SEARCH("imaging",_xlpm.n))),"scientific or industrial imaging system",ISNUMBER(SEARCH("pump",_xlpm.n)),"precision fluid-delivery system",OR(ISNUMBER(SEARCH("reactor",_xlpm.n)),ISNUMBER(SEARCH("autoclave",_xlpm.n)),ISNUMBER(SEARCH("pilot",_xlpm.n))),"laboratory or pilot-process system",OR(ISNUMBER(SEARCH("analyzer",_xlpm.n)),ISNUMBER(SEARCH("spectrometer",_xlpm.n)),ISNUMBER(SEARCH("hplc",_xlpm.n)),ISNUMBER(SEARCH("chrom",_xlpm.n))),"analytical laboratory instrument",OR(ISNUMBER(SEARCH("tester",_xlpm.n)),ISNUMBER(SEARCH("testing machine",_xlpm.n)),ISNUMBER(SEARCH("chamber",_xlpm.n))),"materials or component testing system",OR(ISNUMBER(SEARCH("sensor",_xlpm.n)),ISNUMBER(SEARCH("terminal",_xlpm.n)),ISNUMBER(SEARCH("station",_xlpm.n)),ISNUMBER(SEARCH("satellite",_xlpm.n))),"space or sensing subsystem",ISNUMBER(SEARCH("software",_xlpm.n)),"specialized engineering software platform",TRUE,"specialized "&_xlpm.c&" product"),_xlpm.art,IF(ISNUMBER(SEARCH(LEFT(_xlpm.t,1),"aeiou")),"an ","a "),E67&" is "&_xlpm.art&_xlpm.t&" from "&C67&" designed for application-specific laboratory, engineering or industrial use. It belongs to DIWAN's "&B67&" portfolio; final configuration must be selected against performance, integration and compliance requirements.")} -> ChroZen HPLC is an analytical laboratory instrument from Young In Chromass designed for application-specific laboratory, engineering or industrial use. It belongs to DIWAN's Liquid Chromatography portfolio; final configuration must be selected against performance, integration and compliance requirements. | P67: ="Selection should confirm the model-specific operating range, capacity, accuracy, interfaces, utilities, accessories, standards, environmental limits and service requirements. Final capabilities depend on the approved "&E67&" configuration." -> Selection should confirm the model-specific operating range, capacity, accuracy, interfaces, utilities, accessories, standards, environmental limits and service requirements. Final capabilities depend on the approved ChroZen HPLC configuration. | R67: =B67&" applications; laboratory research, engineering development, quality control and industrial deployment where applicable. Suitability must be confirmed against the user's sample, process, environment and required standards." -> Liquid Chromatography applications; laboratory research, engineering development, quality control and industrial deployment where applicable. Suitability must be confirmed against the user's sample, process, environment and required standards. | T67: =E67&" from "&C67 -> ChroZen HPLC from Young In Chromass | V67: No public downloadable document captured yet; provide the latest approved manufacturer document on request after revision and reuse checks. | W67: ="See other "&B67&" products" -> See other Liquid Chromatography products | X67: =B67&" enquiry → website group enquiry form → category owner assignment" -> Liquid Chromatography enquiry → website group enquiry form → category owner assignment | Y67: =E67&", "&B67&", "&C67&", technical equipment, DIWAN" -> ChroZen HPLC, Liquid Chromatography, Young In Chromass, technical equipment, DIWAN | Z67: https://eng.youngincm.com/goods/list.php?M2_IDX=18659 | AA67: 46257 | AB67: Product Team / Technical Reviewer | AC67: =IF(AND(O67<>"",P67<>"",R67<>"",T67<>"",X67<>"",Y67<>"",Z67<>"",AA67<>"",AB67<>""),IF(AND(Q67<>"",S67<>"",U67<>""),"Ready for approval","Content drafted - assets/specs pending"),IF(COUNTA(O67:AB67)=0,"Not started","In progress")) -> Content drafted - assets/specs pending | AD67: ="Baseline definition created from the official catalog name, partner and category classification ("&G67&"). Model-specific specifications, images and downloadable documents must be extracted from the linked official source and technically approved before publication. Source register reviewed 2026-08-23." -> Baseline definition created from the official catalog name, partner and category classification (One page per product category). Model-specific specifications, images and downloadable documents must be extracted from the linked official source and technically approved before publication. Source register reviewed 2026-08-23. | AG67: Availability, configuration and commercial supply are subject to confirmation by DIWAN and the manufacturer. | AH67: Lead time is confirmed in the formal quotation; do not publish a fixed delivery commitment. | AI67: Publish manufacturer documents only when public access and reuse are permitted; otherwise provide controlled access on request.
A68: =IF(B68=B67,A67,A67+1) -> 13 | B68: Liquid Chromatography | C68: Young In Chromass | D68: South Korea | E68: ChroZen UHPLC | F68: /products/liquid-chromatography | G68: One page per product category | H68: 46257 | I68: ChroZen UHPLC | DIWAN Engineering & Technology Company | J68: chrozen-uhplc | K68: =E68&" is "&IF(ISNUMBER(SEARCH(LEFT(LOWER(B68),1),"aeiou")),"an ","a ")&LOWER(B68)&" product from "&C68&" for application-specific laboratory, engineering or industrial use." -> ChroZen UHPLC is a liquid chromatography product from Young In Chromass for application-specific laboratory, engineering or industrial use. | L68: =E68&" from "&C68&" for "&LOWER(B68)&" applications. Review configuration requirements and request technical information or a quotation from DIWAN." -> ChroZen UHPLC from Young In Chromass for liquid chromatography applications. Review configuration requirements and request technical information or a quotation from DIWAN. | M68: Request technical information or a quote | N68: Baseline definition complete - official specifications and assets pending | O68: {=_xlfn.LET(_xlpm.n,LOWER(E68),_xlpm.c,LOWER(B68),_xlpm.t,_xlfn.IFS(OR(ISNUMBER(SEARCH("lens",_xlpm.n)),ISNUMBER(SEARCH("optic",_xlpm.n)),ISNUMBER(SEARCH("polarizer",_xlpm.n))),"precision optical component",OR(ISNUMBER(SEARCH("camera",_xlpm.n)),ISNUMBER(SEARCH("imaging",_xlpm.n))),"scientific or industrial imaging system",ISNUMBER(SEARCH("pump",_xlpm.n)),"precision fluid-delivery system",OR(ISNUMBER(SEARCH("reactor",_xlpm.n)),ISNUMBER(SEARCH("autoclave",_xlpm.n)),ISNUMBER(SEARCH("pilot",_xlpm.n))),"laboratory or pilot-process system",OR(ISNUMBER(SEARCH("analyzer",_xlpm.n)),ISNUMBER(SEARCH("spectrometer",_xlpm.n)),ISNUMBER(SEARCH("hplc",_xlpm.n)),ISNUMBER(SEARCH("chrom",_xlpm.n))),"analytical laboratory instrument",OR(ISNUMBER(SEARCH("tester",_xlpm.n)),ISNUMBER(SEARCH("testing machine",_xlpm.n)),ISNUMBER(SEARCH("chamber",_xlpm.n))),"materials or component testing system",OR(ISNUMBER(SEARCH("sensor",_xlpm.n)),ISNUMBER(SEARCH("terminal",_xlpm.n)),ISNUMBER(SEARCH("station",_xlpm.n)),ISNUMBER(SEARCH("satellite",_xlpm.n))),"space or sensing subsystem",ISNUMBER(SEARCH("software",_xlpm.n)),"specialized engineering software platform",TRUE,"specialized "&_xlpm.c&" product"),_xlpm.art,IF(ISNUMBER(SEARCH(LEFT(_xlpm.t,1),"aeiou")),"an ","a "),E68&" is "&_xlpm.art&_xlpm.t&" from "&C68&" designed for application-specific laboratory, engineering or industrial use. It belongs to DIWAN's "&B68&" portfolio; final configuration must be selected against performance, integration and compliance requirements.")} -> ChroZen UHPLC is an analytical laboratory instrument from Young In Chromass designed for application-specific laboratory, engineering or industrial use. It belongs to DIWAN's Liquid Chromatography portfolio; final configuration must be selected against performance, integration and compliance requirements. | P68: ="Selection should confirm the model-specific operating range, capacity, accuracy, interfaces, utilities, accessories, standards, environmental limits and service requirements. Final capabilities depend on the approved "&E68&" configuration." -> Selection should confirm the model-specific operating range, capacity, accuracy, interfaces, utilities, accessories, standards, environmental limits and service requirements. Final capabilities depend on the approved ChroZen UHPLC configuration. | R68: =B68&" applications; laboratory research, engineering development, quality control and industrial deployment where applicable. Suitability must be confirmed against the user's sample, process, environment and required standards." -> Liquid Chromatography applications; laboratory research, engineering development, quality control and industrial deployment where applicable. Suitability must be confirmed against the user's sample, process, environment and required standards. | T68: =E68&" from "&C68 -> ChroZen UHPLC from Young In Chromass | V68: No public downloadable document captured yet; provide the latest approved manufacturer document on request after revision and reuse checks. | W68: ="See other "&B68&" products" -> See other Liquid Chromatography products | X68: =B68&" enquiry → website group enquiry form → category owner assignment" -> Liquid Chromatography enquiry → website group enquiry form → category owner assignment | Y68: =E68&", "&B68&", "&C68&", technical equipment, DIWAN" -> ChroZen UHPLC, Liquid Chromatography, Young In Chromass, technical equipment, DIWAN | Z68: https://eng.youngincm.com/goods/list.php?M2_IDX=18659 | AA68: 46257 | AB68: Product Team / Technical Reviewer | AC68: =IF(AND(O68<>"",P68<>"",R68<>"",T68<>"",X68<>"",Y68<>"",Z68<>"",AA68<>"",AB68<>""),IF(AND(Q68<>"",S68<>"",U68<>""),"Ready for approval","Content drafted - assets/specs pending"),IF(COUNTA(O68:AB68)=0,"Not started","In progress")) -> Content drafted - assets/specs pending | AD68: ="Baseline definition created from the official catalog name, partner and category classification ("&G68&"). Model-specific specifications, images and downloadable documents must be extracted from the linked official source and technically approved before publication. Source register reviewed 2026-08-23." -> Baseline definition created from the official catalog name, partner and category classification (One page per product category). Model-specific specifications, images and downloadable documents must be extracted from the linked official source and technically approved before publication. Source register reviewed 2026-08-23. | AG68: Availability, configuration and commercial supply are subject to confirmation by DIWAN and the manufacturer. | AH68: Lead time is confirmed in the formal quotation; do not publish a fixed delivery commitment. | AI68: Publish manufacturer documents only when public access and reuse are permitted; otherwise provide controlled access on request.
A69: =IF(B69=B68,A68,A68+1) -> 13 | B69: Liquid Chromatography | C69: Young In Chromass | D69: South Korea | E69: ChroZen GPC System | F69: /products/liquid-chromatography | G69: One page per product category | H69: 46257 | I69: ChroZen GPC System | DIWAN Engineering & Technology Company | J69: chrozen-gpc-system | K69: =E69&" is "&IF(ISNUMBER(SEARCH(LEFT(LOWER(B69),1),"aeiou")),"an ","a ")&LOWER(B69)&" product from "&C69&" for application-specific laboratory, engineering or industrial use." -> ChroZen GPC System is a liquid chromatography product from Young In Chromass for application-specific laboratory, engineering or industrial use. | L69: =E69&" from "&C69&" for "&LOWER(B69)&" applications. Review configuration requirements and request technical information or a quotation from DIWAN." -> ChroZen GPC System from Young In Chromass for liquid chromatography applications. Review configuration requirements and request technical information or a quotation from DIWAN. | M69: Request technical information or a quote | N69: Baseline definition complete - official specifications and assets pending | O69: {=_xlfn.LET(_xlpm.n,LOWER(E69),_xlpm.c,LOWER(B69),_xlpm.t,_xlfn.IFS(OR(ISNUMBER(SEARCH("lens",_xlpm.n)),ISNUMBER(SEARCH("optic",_xlpm.n)),ISNUMBER(SEARCH("polarizer",_xlpm.n))),"precision optical component",OR(ISNUMBER(SEARCH("camera",_xlpm.n)),ISNUMBER(SEARCH("imaging",_xlpm.n))),"scientific or industrial imaging system",ISNUMBER(SEARCH("pump",_xlpm.n)),"precision fluid-delivery system",OR(ISNUMBER(SEARCH("reactor",_xlpm.n)),ISNUMBER(SEARCH("autoclave",_xlpm.n)),ISNUMBER(SEARCH("pilot",_xlpm.n))),"laboratory or pilot-process system",OR(ISNUMBER(SEARCH("analyzer",_xlpm.n)),ISNUMBER(SEARCH("spectrometer",_xlpm.n)),ISNUMBER(SEARCH("hplc",_xlpm.n)),ISNUMBER(SEARCH("chrom",_xlpm.n))),"analytical laboratory instrument",OR(ISNUMBER(SEARCH("tester",_xlpm.n)),ISNUMBER(SEARCH("testing machine",_xlpm.n)),ISNUMBER(SEARCH("chamber",_xlpm.n))),"materials or component testing system",OR(ISNUMBER(SEARCH("sensor",_xlpm.n)),ISNUMBER(SEARCH("terminal",_xlpm.n)),ISNUMBER(SEARCH("station",_xlpm.n)),ISNUMBER(SEARCH("satellite",_xlpm.n))),"space or sensing subsystem",ISNUMBER(SEARCH("software",_xlpm.n)),"specialized engineering software platform",TRUE,"specialized "&_xlpm.c&" product"),_xlpm.art,IF(ISNUMBER(SEARCH(LEFT(_xlpm.t,1),"aeiou")),"an ","a "),E69&" is "&_xlpm.art&_xlpm.t&" from "&C69&" designed for application-specific laboratory, engineering or industrial use. It belongs to DIWAN's "&B69&" portfolio; final configuration must be selected against performance, integration and compliance requirements.")} -> ChroZen GPC System is a specialized liquid chromatography product from Young In Chromass designed for application-specific laboratory, engineering or industrial use. It belongs to DIWAN's Liquid Chromatography portfolio; final configuration must be selected against performance, integration and compliance requirements. | P69: ="Selection should confirm the model-specific operating range, capacity, accuracy, interfaces, utilities, accessories, standards, environmental limits and service requirements. Final capabilities depend on the approved "&E69&" configuration." -> Selection should confirm the model-specific operating range, capacity, accuracy, interfaces, utilities, accessories, standards, environmental limits and service requirements. Final capabilities depend on the approved ChroZen GPC System configuration. | R69: =B69&" applications; laboratory research, engineering development, quality control and industrial deployment where applicable. Suitability must be confirmed against the user's sample, process, environment and required standards." -> Liquid Chromatography applications; laboratory research, engineering development, quality control and industrial deployment where applicable. Suitability must be confirmed against the user's sample, process, environment and required standards. | T69: =E69&" from "&C69 -> ChroZen GPC System from Young In Chromass | V69: No public downloadable document captured yet; provide the latest approved manufacturer document on request after revision and reuse checks. | W69: ="See other "&B69&" products" -> See other Liquid Chromatography products | X69: =B69&" enquiry → website group enquiry form → category owner assignment" -> Liquid Chromatography enquiry → website group enquiry form → category owner assignment | Y69: =E69&", "&B69&", "&C69&", technical equipment, DIWAN" -> ChroZen GPC System, Liquid Chromatography, Young In Chromass, technical equipment, DIWAN | Z69: https://eng.youngincm.com/goods/list.php?M2_IDX=18659 | AA69: 46257 | AB69: Product Team / Technical Reviewer | AC69: =IF(AND(O69<>"",P69<>"",R69<>"",T69<>"",X69<>"",Y69<>"",Z69<>"",AA69<>"",AB69<>""),IF(AND(Q69<>"",S69<>"",U69<>""),"Ready for approval","Content drafted - assets/specs pending"),IF(COUNTA(O69:AB69)=0,"Not started","In progress")) -> Content drafted - assets/specs pending | AD69: ="Baseline definition created from the official catalog name, partner and category classification ("&G69&"). Model-specific specifications, images and downloadable documents must be extracted from the linked official source and technically approved before publication. Source register reviewed 2026-08-23." -> Baseline definition created from the official catalog name, partner and category classification (One page per product category). Model-specific specifications, images and downloadable documents must be extracted from the linked official source and technically approved before publication. Source register reviewed 2026-08-23. | AG69: Availability, configuration and commercial supply are subject to confirmation by DIWAN and the manufacturer. | AH69: Lead time is confirmed in the formal quotation; do not publish a fixed delivery commitment. | AI69: Publish manufacturer documents only when public access and reuse are permitted; otherwise provide controlled access on request.
